{"skeleton":{"hash":"ndpjQ+MFA/AfQ3K4SO6Efxeu+s4","spine":"3.8.84","x":-691,"y":-1029,"width":1382,"height":2077.02,"images":"./images/","audio":""},"bones":[{"name":"root"},{"name":"bone","parent":"root"},{"name":"back_ef","parent":"bone"},{"name":"back_ef_1_1","parent":"back_ef","x":570.54,"y":821.37},{"name":"back_ef_2_1","parent":"back_ef","color":"9b9b9b00"},{"name":"back_ef_3_1","parent":"back_ef"},{"name":"flower","parent":"bone"},{"name":"flower_1","parent":"flower","x":541.55,"y":820.5},{"name":"flower_2","parent":"flower","x":339.5,"y":676.12},{"name":"flower_3","parent":"flower","x":537.58,"y":489.87},{"name":"flower_4","parent":"flower","x":378.79,"y":254.66},{"name":"flower_5","parent":"flower","x":543.76,"y":202.62},{"name":"flower_6","parent":"flower","x":465.54,"y":-116.6},{"name":"flower_7","parent":"flower","x":464.51,"y":-337.14},{"name":"flower_8","parent":"flower","x":-526.78,"y":628.64},{"name":"flower_9","parent":"flower","x":-508.72,"y":172.33},{"name":"flower_10","parent":"flower","x":-282.37,"y":7.54},{"name":"flower_11","parent":"flower","x":-395.86,"y":0.52},{"name":"flower_12","parent":"flower","x":-309.95,"y":-166.22},{"name":"flower_13","parent":"flower","x":-455.88,"y":-480.31},{"name":"flower_14","parent":"flower","x":-85.76,"y":-656.1},{"name":"flower_15","parent":"flower","x":-318.69,"y":-774.59},{"name":"weapon_line","parent":"bone","x":210,"y":-180},{"name":"weapon_line_1","parent":"weapon_line","length":450.31,"rotation":85.63,"x":-0.51,"y":-4.64,"scaleX":1.0284,"scaleY":1.0284},{"name":"weapon_line_2","parent":"weapon_line","length":87.66,"rotation":59.1},{"name":"weapon_line_3","parent":"weapon_line","length":94.06,"rotation":136.42},{"name":"weapon_line_4","parent":"weapon_line","length":42.01,"rotation":30.8},{"name":"weapon_line_5","parent":"weapon_line","length":62.04,"rotation":172.89},{"name":"weapon_line_6","parent":"weapon_line","length":35.6,"rotation":-27.42},{"name":"weapon_line_7","parent":"weapon_line","length":35.99,"rotation":-103.58},{"name":"front_ef","parent":"bone","x":450,"y":-560},{"name":"front_ef_1_1","parent":"front_ef","length":190.82,"rotation":72.85,"x":74.39,"y":540.22},{"name":"front_ef_2_1","parent":"front_ef","length":182.83,"rotation":85.76,"x":-13.4,"y":675.28},{"name":"front_ef_3_1","parent":"front_ef","length":147.89,"rotation":117.26,"x":-810.8,"y":1353.07},{"name":"front_ef_4_1","parent":"front_ef","length":127.58,"rotation":121.23,"x":-900.87,"y":873.85},{"name":"front_ef_5_1","parent":"front_ef","length":152.14,"rotation":138.62,"x":-608.19,"y":353.62},{"name":"front_ef_6_1","parent":"front_ef","length":68.83,"rotation":66.29,"x":72.02,"y":125.38},{"name":"front_ef_7_1","parent":"front_ef","length":77.72,"rotation":25.59,"x":64.95,"y":22.9},{"name":"front_ef_8_1","parent":"front_ef","length":98.51,"rotation":-65.14,"x":55.23,"y":-82.06},{"name":"front_ef_9_1","parent":"front_ef","length":123.68,"rotation":-109.56,"x":17.89,"y":-147.79},{"name":"front_ef_10_1","parent":"front_ef","length":105.34,"rotation":-135.49,"x":-91.74,"y":-208.52},{"name":"front_ef_11_1","parent":"front_ef","length":107.81,"rotation":-162.43,"x":-566.93,"y":-395.51},{"name":"front_ef_12_1","parent":"front_ef","length":128.47,"rotation":-143.26,"x":-40.21,"y":-79.85},{"name":"front_ef_13_1","parent":"front_ef","length":168.28,"rotation":-168.07,"x":-268.94,"y":-117.94},{"name":"front_ef_14_1","parent":"front_ef","length":87.57,"rotation":155.29,"x":-814.74,"y":8.59},{"name":"front_ef_15_1","parent":"front_ef","length":106.18,"rotation":-179.74,"x":-138.94,"y":-27.31},{"name":"purple","parent":"bone"},{"name":"purple_1","parent":"purple","x":330.8,"y":829.7},{"name":"purple_2","parent":"purple","x":-105.97,"y":881.31},{"name":"purple_3","parent":"purple","x":-147.2,"y":823.32},{"name":"purple_4","parent":"purple","x":-408.72,"y":685.56},{"name":"purple_5","parent":"purple","x":-383.7,"y":644.71},{"name":"purple_6","parent":"purple","x":484.53,"y":370.83},{"name":"purple_7","parent":"purple","x":-217.12,"y":-51.64},{"name":"purple_8","parent":"purple","x":-246.16,"y":-106.79},{"name":"purple_9","parent":"purple","x":-436.62,"y":-662.14},{"name":"flare","parent":"bone","x":211.78,"y":-183.76},{"name":"shadow","parent":"bone"},{"name":"shadow2","parent":"bone"},{"name":"shadow3","parent":"bone"},{"name":"shadow4","parent":"bone"},{"name":"back_ef_2_2","parent":"back_ef","color":"9b9b9b00"},{"name":"back_ef_2_3","parent":"back_ef","color":"9b9b9b00"},{"name":"back_ef_1_2","parent":"back_ef","x":570.54,"y":821.37},{"name":"back_ef_1_3","parent":"back_ef","x":570.54,"y":821.37},{"name":"back_ef_3_2","parent":"back_ef"},{"name":"back_ef_3_3","parent":"back_ef"},{"name":"front_ef_1_2","parent":"front_ef","length":190.82,"rotation":72.85,"x":74.39,"y":540.22},{"name":"front_ef_2_2","parent":"front_ef","length":182.83,"rotation":85.76,"x":-13.4,"y":675.28},{"name":"front_ef_3_2","parent":"front_ef","length":147.89,"rotation":117.26,"x":-810.8,"y":1353.07},{"name":"front_ef_4_2","parent":"front_ef","length":127.58,"rotation":121.23,"x":-900.87,"y":873.85},{"name":"front_ef_5_2","parent":"front_ef","length":152.14,"rotation":138.62,"x":-608.19,"y":353.62},{"name":"front_ef_6_2","parent":"front_ef","length":68.83,"rotation":66.29,"x":72.02,"y":125.38},{"name":"front_ef_7_2","parent":"front_ef","length":77.72,"rotation":25.59,"x":64.95,"y":22.9},{"name":"front_ef_8_2","parent":"front_ef","length":98.51,"rotation":-65.14,"x":55.23,"y":-82.06},{"name":"front_ef_9_2","parent":"front_ef","length":123.68,"rotation":-109.56,"x":17.89,"y":-147.79},{"name":"front_ef_10_2","parent":"front_ef","length":105.34,"rotation":-135.49,"x":-91.74,"y":-208.52},{"name":"front_ef_11_2","parent":"front_ef","length":107.81,"rotation":-162.43,"x":-566.93,"y":-395.51},{"name":"front_ef_12_2","parent":"front_ef","length":128.47,"rotation":-143.26,"x":-40.21,"y":-79.85},{"name":"front_ef_13_2","parent":"front_ef","length":168.28,"rotation":-168.07,"x":-268.94,"y":-117.94},{"name":"front_ef_14_2","parent":"front_ef","length":87.57,"rotation":155.29,"x":-814.74,"y":8.59},{"name":"front_ef_15_2","parent":"front_ef","length":106.18,"rotation":-179.74,"x":-138.94,"y":-27.31}],"slots":[{"name":"BG","bone":"bone","attachment":"BG"},{"name":"shadow","bone":"shadow","color":"39393962","attachment":"shadow"},{"name":"shadow2","bone":"shadow2","color":"39393962","attachment":"shadow"},{"name":"shadow3","bone":"shadow3","color":"39393962","attachment":"shadow"},{"name":"shadow4","bone":"shadow4","color":"39393962","attachment":"shadow"},{"name":"back_ef_3_2","bone":"back_ef_3_1","color":"ffffff4a","attachment":"back_ef_3_2"},{"name":"back_ef_3_3","bone":"back_ef_3_2","color":"ffffff4a","attachment":"back_ef_3_2"},{"name":"back_ef_3_5","bone":"back_ef_3_3","color":"ffffff4a","attachment":"back_ef_3_2"},{"name":"back_ef_3_1","bone":"back_ef_3_1","color":"ffffff71","attachment":"back_ef_3_1","blend":"additive"},{"name":"back_ef_3_4","bone":"back_ef_3_2","color":"ffffff71","attachment":"back_ef_3_1","blend":"additive"},{"name":"back_ef_3_6","bone":"back_ef_3_3","color":"ffffff71","attachment":"back_ef_3_1","blend":"additive"},{"name":"back_ef_2_2","bone":"back_ef_2_1","color":"ffffff69","attachment":"back_ef_2_2"},{"name":"back_ef_2_3","bone":"back_ef_2_2","color":"ffffff27","attachment":"back_ef_2_2"},{"name":"back_ef_2_5","bone":"back_ef_2_3","color":"ffffff27","attachment":"back_ef_2_2"},{"name":"back_ef_2_1","bone":"back_ef_2_1","color":"ffffff5b","attachment":"back_ef_2_1","blend":"additive"},{"name":"back_ef_2_4","bone":"back_ef_2_2","color":"ffffff27","attachment":"back_ef_2_1","blend":"additive"},{"name":"back_ef_2_6","bone":"back_ef_2_3","color":"ffffff27","attachment":"back_ef_2_1","blend":"additive"},{"name":"back_ef_1_2","bone":"back_ef_1_1","attachment":"back_ef_1_2"},{"name":"back_ef_1_3","bone":"back_ef_1_2","color":"ffffff23","attachment":"back_ef_1_2"},{"name":"back_ef_1_5","bone":"back_ef_1_3","color":"ffffff23","attachment":"back_ef_1_2"},{"name":"back_ef_1_1","bone":"back_ef_1_1","attachment":"back_ef_1_1","blend":"additive"},{"name":"back_ef_1_4","bone":"back_ef_1_2","color":"ffffff23","attachment":"back_ef_1_1","blend":"additive"},{"name":"back_ef_1_6","bone":"back_ef_1_3","color":"ffffff23","attachment":"back_ef_1_1","blend":"additive"},{"name":"character","bone":"bone","attachment":"character"},{"name":"flower_15","bone":"flower_15","attachment":"flower_15"},{"name":"flower_14","bone":"flower_14","attachment":"flower_14"},{"name":"flower_13","bone":"flower_13","attachment":"flower_13"},{"name":"flower_12","bone":"flower_12","attachment":"flower_12"},{"name":"flower_11","bone":"flower_11","attachment":"flower_11"},{"name":"flower_10","bone":"flower_10","attachment":"flower_10"},{"name":"flower_9","bone":"flower_9","attachment":"flower_9"},{"name":"flower_8","bone":"flower_8","attachment":"flower_8"},{"name":"flower_7","bone":"flower_7","attachment":"flower_7"},{"name":"flower_6","bone":"flower_6","attachment":"flower_6"},{"name":"flower_5","bone":"flower_5","attachment":"flower_5"},{"name":"flower_4","bone":"flower_4","attachment":"flower_4"},{"name":"flower_3","bone":"flower_3","attachment":"flower_3"},{"name":"flower_2","bone":"flower_2","attachment":"flower_2"},{"name":"flower_1","bone":"flower_1","attachment":"flower_1"},{"name":"front_ef_15","bone":"front_ef_15_1","attachment":"front_ef_15"},{"name":"front_ef_30","bone":"front_ef_15_2","attachment":"front_ef_15"},{"name":"front_ef_14","bone":"front_ef_14_1","attachment":"front_ef_14"},{"name":"front_ef_29","bone":"front_ef_14_2","attachment":"front_ef_14"},{"name":"front_ef_13","bone":"front_ef_13_1","attachment":"front_ef_13"},{"name":"front_ef_28","bone":"front_ef_13_2","attachment":"front_ef_13"},{"name":"front_ef_12","bone":"front_ef_12_1","attachment":"front_ef_12"},{"name":"front_ef_27","bone":"front_ef_12_2","attachment":"front_ef_12"},{"name":"front_ef_11","bone":"front_ef_11_1","attachment":"front_ef_11"},{"name":"front_ef_26","bone":"front_ef_11_2","attachment":"front_ef_11"},{"name":"front_ef_10","bone":"front_ef_10_1","attachment":"front_ef_10"},{"name":"front_ef_25","bone":"front_ef_10_2","attachment":"front_ef_10"},{"name":"front_ef_9","bone":"front_ef_9_1","attachment":"front_ef_9"},{"name":"front_ef_24","bone":"front_ef_9_2","attachment":"front_ef_9"},{"name":"front_ef_8","bone":"front_ef_8_1","attachment":"front_ef_8"},{"name":"front_ef_23","bone":"front_ef_8_2","attachment":"front_ef_8"},{"name":"front_ef_7","bone":"front_ef_7_1","attachment":"front_ef_7"},{"name":"front_ef_22","bone":"front_ef_7_2","attachment":"front_ef_7"},{"name":"front_ef_6","bone":"front_ef_6_1","attachment":"front_ef_6"},{"name":"front_ef_21","bone":"front_ef_6_2","attachment":"front_ef_6"},{"name":"front_ef_5","bone":"front_ef_5_1","attachment":"front_ef_5"},{"name":"front_ef_20","bone":"front_ef_5_2","attachment":"front_ef_5"},{"name":"front_ef_4","bone":"front_ef_4_1","attachment":"front_ef_4"},{"name":"front_ef_19","bone":"front_ef_4_2","attachment":"front_ef_4"},{"name":"front_ef_3","bone":"front_ef_3_1","attachment":"front_ef_3"},{"name":"front_ef_18","bone":"front_ef_3_2","attachment":"front_ef_3"},{"name":"front_ef_2","bone":"front_ef_2_1","attachment":"front_ef_2"},{"name":"front_ef_17","bone":"front_ef_2_2","attachment":"front_ef_2"},{"name":"front_ef_1","bone":"front_ef_1_1","attachment":"front_ef_1"},{"name":"front_ef_16","bone":"front_ef_1_2","attachment":"front_ef_1"},{"name":"purple_9","bone":"purple_9","attachment":"purple_9","blend":"additive"},{"name":"purple_8","bone":"purple_8","attachment":"purple_8","blend":"additive"},{"name":"purple_7","bone":"purple_7","attachment":"purple_7","blend":"additive"},{"name":"purple_6","bone":"purple_6","attachment":"purple_6","blend":"additive"},{"name":"purple_5","bone":"purple_5","attachment":"purple_5","blend":"additive"},{"name":"purple_4","bone":"purple_4","attachment":"purple_4","blend":"additive"},{"name":"purple_3","bone":"purple_3","attachment":"purple_3","blend":"additive"},{"name":"purple_2","bone":"purple_2","attachment":"purple_2","blend":"additive"},{"name":"purple_1","bone":"purple_1","attachment":"purple_1","blend":"additive"},{"name":"weapon_line_7","bone":"weapon_line_7","attachment":"weapon_line_7","blend":"additive"},{"name":"weapon_line_6","bone":"weapon_line_6","attachment":"weapon_line_6","blend":"additive"},{"name":"weapon_line_5","bone":"weapon_line_5","attachment":"weapon_line_5","blend":"additive"},{"name":"weapon_line_4","bone":"weapon_line_4","attachment":"weapon_line_4","blend":"additive"},{"name":"weapon_line_3","bone":"weapon_line_3","attachment":"weapon_line_3","blend":"additive"},{"name":"weapon_line_2","bone":"weapon_line_2","attachment":"weapon_line_2","blend":"additive"},{"name":"weapon_line_1","bone":"weapon_line_1","attachment":"weapon_line_1","blend":"additive"},{"name":"flare","bone":"flare","attachment":"flare","blend":"screen"},{"name":"template","bone":"bone"}],"skins":[{"name":"default","attachments":{"BG":{"BG":{"x":2,"y":-2,"width":1090,"height":1766}},"back_ef_1_1":{"back_ef_1_1":{"type":"mesh","uvs":[1,1,0,1,0,0,1,0],"triangles":[1,2,3,1,3,0],"vertices":[120.46,-97.37,-236.54,-97.37,-236.54,86.63,120.46,86.63],"hull":4,"edges":[0,2,2,4,4,6,0,6],"width":357,"height":184}},"back_ef_1_2":{"back_ef_1_2":{"type":"mesh","uvs":[1,1,0,1,0,0,1,0],"triangles":[1,2,3,1,3,0],"vertices":[120.46,-98.37,-233.54,-98.37,-233.54,69.63,120.46,69.63],"hull":4,"edges":[0,2,2,4,4,6,0,6],"width":354,"height":168}},"back_ef_1_3":{"back_ef_1_2":{"type":"mesh","uvs":[1,1,0,1,0,0,1,0],"triangles":[1,2,3,1,3,0],"vertices":[120.46,-98.37,-233.54,-98.37,-233.54,69.63,120.46,69.63],"hull":4,"edges":[0,2,2,4,4,6,0,6],"width":354,"height":168}},"back_ef_1_4":{"back_ef_1_1":{"type":"mesh","uvs":[1,1,0,1,0,0,1,0],"triangles":[1,2,3,1,3,0],"vertices":[120.46,-97.37,-236.54,-97.37,-236.54,86.63,120.46,86.63],"hull":4,"edges":[0,2,2,4,4,6,0,6],"width":357,"height":184}},"back_ef_1_5":{"back_ef_1_2":{"type":"mesh","uvs":[1,1,0,1,0,0,1,0],"triangles":[1,2,3,1,3,0],"vertices":[120.46,-98.37,-233.54,-98.37,-233.54,69.63,120.46,69.63],"hull":4,"edges":[0,2,2,4,4,6,0,6],"width":354,"height":168}},"back_ef_1_6":{"back_ef_1_1":{"type":"mesh","uvs":[1,1,0,1,0,0,1,0],"triangles":[1,2,3,1,3,0],"vertices":[120.46,-97.37,-236.54,-97.37,-236.54,86.63,120.46,86.63],"hull":4,"edges":[0,2,2,4,4,6,0,6],"width":357,"height":184}},"back_ef_2_1":{"back_ef_2_1":{"type":"mesh","uvs":[1,1,0,1,0,0,1,0],"triangles":[1,2,3,1,3,0],"vertices":[672,-167,-665,-167,-665,981,672,981],"hull":4,"edges":[0,2,2,4,4,6,0,6],"width":1337,"height":1148}},"back_ef_2_2":{"back_ef_2_2":{"type":"mesh","uvs":[1,1,0,1,0,0,1,0],"triangles":[1,2,3,1,3,0],"vertices":[662,-152,-660,-152,-660,951,662,951],"hull":4,"edges":[0,2,2,4,4,6,0,6],"width":1322,"height":1103}},"back_ef_2_3":{"back_ef_2_2":{"type":"mesh","uvs":[1,1,0,1,0,0,1,0],"triangles":[1,2,3,1,3,0],"vertices":[662,-152,-660,-152,-660,951,662,951],"hull":4,"edges":[0,2,2,4,4,6,0,6],"width":1322,"height":1103}},"back_ef_2_4":{"back_ef_2_1":{"type":"mesh","uvs":[1,1,0,1,0,0,1,0],"triangles":[1,2,3,1,3,0],"vertices":[672,-167,-665,-167,-665,981,672,981],"hull":4,"edges":[0,2,2,4,4,6,0,6],"width":1337,"height":1148}},"back_ef_2_5":{"back_ef_2_2":{"type":"mesh","uvs":[1,1,0,1,0,0,1,0],"triangles":[1,2,3,1,3,0],"vertices":[662,-152,-660,-152,-660,951,662,951],"hull":4,"edges":[0,2,2,4,4,6,0,6],"width":1322,"height":1103}},"back_ef_2_6":{"back_ef_2_1":{"type":"mesh","uvs":[1,1,0,1,0,0,1,0],"triangles":[1,2,3,1,3,0],"vertices":[672,-167,-665,-167,-665,981,672,981],"hull":4,"edges":[0,2,2,4,4,6,0,6],"width":1337,"height":1148}},"back_ef_3_1":{"back_ef_3_1":{"type":"mesh","uvs":[1,1,0,1,0,0,1,0],"triangles":[1,2,3,1,3,0],"vertices":[205,378,-370,378,-370,598,205,598],"hull":4,"edges":[0,2,2,4,4,6,0,6],"width":575,"height":220}},"back_ef_3_2":{"back_ef_3_2":{"type":"mesh","uvs":[1,1,0,1,0,0,1,0],"triangles":[1,2,3,1,3,0],"vertices":[189,394,-350,394,-350,574,189,574],"hull":4,"edges":[0,2,2,4,4,6,0,6],"width":539,"height":180}},"back_ef_3_3":{"back_ef_3_2":{"type":"mesh","uvs":[1,1,0,1,0,0,1,0],"triangles":[1,2,3,1,3,0],"vertices":[189,394,-350,394,-350,574,189,574],"hull":4,"edges":[0,2,2,4,4,6,0,6],"width":539,"height":180}},"back_ef_3_4":{"back_ef_3_1":{"type":"mesh","uvs":[1,1,0,1,0,0,1,0],"triangles":[1,2,3,1,3,0],"vertices":[205,378,-370,378,-370,598,205,598],"hull":4,"edges":[0,2,2,4,4,6,0,6],"width":575,"height":220}},"back_ef_3_5":{"back_ef_3_2":{"type":"mesh","uvs":[1,1,0,1,0,0,1,0],"triangles":[1,2,3,1,3,0],"vertices":[189,394,-350,394,-350,574,189,574],"hull":4,"edges":[0,2,2,4,4,6,0,6],"width":539,"height":180}},"back_ef_3_6":{"back_ef_3_1":{"type":"mesh","uvs":[1,1,0,1,0,0,1,0],"triangles":[1,2,3,1,3,0],"vertices":[205,378,-370,378,-370,598,205,598],"hull":4,"edges":[0,2,2,4,4,6,0,6],"width":575,"height":220}},"character":{"character":{"y":-34.5,"width":1082,"height":1689}},"flare":{"flare":{"x":12.72,"y":-10.74,"width":385,"height":409}},"flower_1":{"flower_1":{"type":"mesh","uvs":[1,1,0,1,0,0,1,0],"triangles":[1,2,3,1,3,0],"vertices":[21.45,-13.5,-27.55,-13.5,-27.55,9.5,21.45,9.5],"hull":4,"edges":[0,2,2,4,4,6,0,6],"width":49,"height":23}},"flower_10":{"flower_10":{"type":"mesh","uvs":[1,1,0,1,0,0,1,0],"triangles":[1,2,3,1,3,0],"vertices":[20.37,-21.54,-15.63,-21.54,-15.63,26.46,20.37,26.46],"hull":4,"edges":[0,2,2,4,4,6,0,6],"width":36,"height":48}},"flower_11":{"flower_11":{"type":"mesh","uvs":[1,1,0,1,0,0,1,0],"triangles":[1,2,3,1,3,0],"vertices":[29.86,-16.52,-22.14,-16.52,-22.14,23.48,29.86,23.48],"hull":4,"edges":[0,2,2,4,4,6,0,6],"width":52,"height":40}},"flower_12":{"flower_12":{"type":"mesh","uvs":[1,1,0,1,0,0,1,0],"triangles":[1,2,3,1,3,0],"vertices":[49.95,-20.78,-31.05,-20.78,-31.05,32.22,49.95,32.22],"hull":4,"edges":[0,2,2,4,4,6,0,6],"width":81,"height":53}},"flower_13":{"flower_13":{"type":"mesh","uvs":[1,1,0,1,0,0,1,0],"triangles":[1,2,3,1,3,0],"vertices":[36.88,-16.69,-23.12,-16.69,-23.12,10.31,36.88,10.31],"hull":4,"edges":[0,2,2,4,4,6,0,6],"width":60,"height":27}},"flower_14":{"flower_14":{"type":"mesh","uvs":[1,1,0,1,0,0,1,0],"triangles":[1,2,3,1,3,0],"vertices":[22.76,-11.9,-29.24,-11.9,-29.24,15.1,22.76,15.1],"hull":4,"edges":[0,2,2,4,4,6,0,6],"width":52,"height":27}},"flower_15":{"flower_15":{"type":"mesh","uvs":[1,1,0,1,0,0,1,0],"triangles":[1,2,3,1,3,0],"vertices":[24.69,-25.41,-13.31,-25.41,-13.31,21.59,24.69,21.59],"hull":4,"edges":[0,2,2,4,4,6,0,6],"width":38,"height":47}},"flower_2":{"flower_2":{"type":"mesh","uvs":[1,1,0,1,0,0,1,0],"triangles":[1,2,3,1,3,0],"vertices":[28.5,-33.12,-36.5,-33.12,-36.5,33.88,28.5,33.88],"hull":4,"edges":[0,2,2,4,4,6,0,6],"width":65,"height":67}},"flower_3":{"flower_3":{"type":"mesh","uvs":[1,1,0,1,0,0,1,0],"triangles":[1,2,3,1,3,0],"vertices":[24.42,-25.87,-17.58,-25.87,-17.58,15.13,24.42,15.13],"hull":4,"edges":[0,2,2,4,4,6,0,6],"width":42,"height":41}},"flower_4":{"flower_4":{"type":"mesh","uvs":[1,1,0,1,0,0,1,0],"triangles":[1,2,3,1,3,0],"vertices":[22.21,-23.66,-22.79,-23.66,-22.79,15.34,22.21,15.34],"hull":4,"edges":[0,2,2,4,4,6,0,6],"width":45,"height":39}},"flower_5":{"flower_5":{"type":"mesh","uvs":[1,1,0,1,0,0,1,0],"triangles":[1,2,3,1,3,0],"vertices":[32.24,-45.62,-23.76,-45.62,-23.76,25.38,32.24,25.38],"hull":4,"edges":[0,2,2,4,4,6,0,6],"width":56,"height":71}},"flower_6":{"flower_6":{"type":"mesh","uvs":[1,1,0,1,0,0,1,0],"triangles":[1,2,3,1,3,0],"vertices":[15.46,-9.4,-22.54,-9.4,-22.54,16.6,15.46,16.6],"hull":4,"edges":[0,2,2,4,4,6,0,6],"width":38,"height":26}},"flower_7":{"flower_7":{"type":"mesh","uvs":[1,1,0,1,0,0,1,0],"triangles":[1,2,3,1,3,0],"vertices":[28.49,-51.86,-42.51,-51.86,-42.51,25.14,28.49,25.14],"hull":4,"edges":[0,2,2,4,4,6,0,6],"width":71,"height":77}},"flower_8":{"flower_8":{"type":"mesh","uvs":[1,1,0,1,0,0,1,0],"triangles":[1,2,3,1,3,0],"vertices":[23.78,-20.64,-14.22,-20.64,-14.22,26.36,23.78,26.36],"hull":4,"edges":[0,2,2,4,4,6,0,6],"width":38,"height":47}},"flower_9":{"flower_9":{"type":"mesh","uvs":[1,1,0,1,0,0,1,0],"triangles":[1,2,3,1,3,0],"vertices":[18.72,-29.33,-11.28,-29.33,-11.28,17.67,18.72,17.67],"hull":4,"edges":[0,2,2,4,4,6,0,6],"width":30,"height":47}},"front_ef_1":{"front_ef_1":{"type":"mesh","uvs":[1,1,0,1,0,0,1,0],"triangles":[1,2,3,1,3,0],"vertices":[-8.53,-125.72,-49.22,6.15,805.01,269.8,845.71,137.94],"hull":4,"edges":[0,2,2,4,4,6,0,6],"width":138,"height":894}},"front_ef_10":{"front_ef_10":{"type":"mesh","uvs":[1,1,0,1,0,0,1,0],"triangles":[1,2,3,1,3,0],"vertices":[172.11,196.08,498.7,-125.01,305.91,-321.11,-20.69,-0.02],"hull":4,"edges":[0,2,2,4,4,6,0,6],"width":458,"height":275}},"front_ef_11":{"front_ef_11":{"type":"mesh","uvs":[1,1,0,1,0,0,1,0],"triangles":[1,2,3,1,3,0],"vertices":[2.12,62.77,228.07,-8.78,204.82,-82.18,-21.12,-10.63],"hull":4,"edges":[0,2,2,4,4,6,0,6],"width":237,"height":77}},"front_ef_12":{"front_ef_12":{"type":"mesh","uvs":[1,1,0,1,0,0,1,0],"triangles":[1,2,3,1,3,0],"vertices":[158.16,249,1058.08,-422.77,875.63,-667.18,-24.29,4.59],"hull":4,"edges":[0,2,2,4,4,6,0,6],"width":1123,"height":305}},"front_ef_13":{"front_ef_13":{"type":"mesh","uvs":[1,1,0,1,0,0,1,0],"triangles":[1,2,3,1,3,0],"vertices":[1.92,62,865.84,-120.55,812.5,-372.98,-51.42,-190.42],"hull":4,"edges":[0,2,2,4,4,6,0,6],"width":883,"height":258}},"front_ef_14":{"front_ef_14":{"type":"mesh","uvs":[1,1,0,1,0,0,1,0],"triangles":[1,2,3,1,3,0],"vertices":[-16.35,7.44,282.52,144.99,348.99,0.55,50.12,-137],"hull":4,"edges":[0,2,2,4,4,6,0,6],"width":329,"height":159}},"front_ef_15":{"front_ef_15":{"type":"mesh","uvs":[1,1,0,1,0,0,1,0],"triangles":[1,2,3,1,3,0],"vertices":[-15.68,58.76,1002.31,54.21,999.3,-621.78,-18.69,-617.23],"hull":4,"edges":[0,2,2,4,4,6,0,6],"width":1018,"height":676}},"front_ef_16":{"front_ef_1":{"type":"mesh","uvs":[1,1,0,1,0,0,1,0],"triangles":[1,2,3,1,3,0],"vertices":[-8.53,-125.72,-49.22,6.15,805.01,269.8,845.71,137.94],"hull":4,"edges":[0,2,2,4,4,6,0,6],"width":138,"height":894}},"front_ef_17":{"front_ef_2":{"type":"mesh","uvs":[1,1,0,1,0,0,1,0],"triangles":[1,2,3,1,3,0],"vertices":[-17.83,-33.81,-26.85,87.86,897.62,156.34,906.63,34.67],"hull":4,"edges":[0,2,2,4,4,6,0,6],"width":122,"height":927}},"front_ef_18":{"front_ef_3":{"type":"mesh","uvs":[1,1,0,1,0,0,1,0],"triangles":[1,2,3,1,3,0],"vertices":[-18.85,-8.06,51.67,128.85,273.03,14.81,202.5,-122.09],"hull":4,"edges":[0,2,2,4,4,6,0,6],"width":154,"height":249}},"front_ef_19":{"front_ef_4":{"type":"mesh","uvs":[1,1,0,1,0,0,1,0],"triangles":[1,2,3,1,3,0],"vertices":[-22.82,-7.07,83.46,168.23,381.89,-12.71,275.61,-188.01],"hull":4,"edges":[0,2,2,4,4,6,0,6],"width":205,"height":349}},"front_ef_2":{"front_ef_2":{"type":"mesh","uvs":[1,1,0,1,0,0,1,0],"triangles":[1,2,3,1,3,0],"vertices":[-17.83,-33.81,-26.85,87.86,897.62,156.34,906.63,34.67],"hull":4,"edges":[0,2,2,4,4,6,0,6],"width":122,"height":927}},"front_ef_20":{"front_ef_5":{"type":"mesh","uvs":[1,1,0,1,0,0,1,0],"triangles":[1,2,3,1,3,0],"vertices":[-29.62,0.06,233.01,231.42,496.1,-67.22,233.47,-298.58],"hull":4,"edges":[0,2,2,4,4,6,0,6],"width":350,"height":398}},"front_ef_21":{"front_ef_6":{"type":"mesh","uvs":[1,1,0,1,0,0,1,0],"triangles":[1,2,3,1,3,0],"vertices":[12.23,-71.06,-22.36,7.68,176.32,94.95,210.91,16.21],"hull":4,"edges":[0,2,2,4,4,6,0,6],"width":86,"height":217}},"front_ef_22":{"front_ef_7":{"type":"mesh","uvs":[1,1,0,1,0,0,1,0],"triangles":[1,2,3,1,3,0],"vertices":[135.54,-101.4,-29.5,-22.35,88,222.97,253.05,143.91],"hull":4,"edges":[0,2,2,4,4,6,0,6],"width":183,"height":272}},"front_ef_23":{"front_ef_8":{"type":"mesh","uvs":[1,1,0,1,0,0,1,0],"triangles":[1,2,3,1,3,0],"vertices":[429.19,5.86,344.26,-177.42,-31.37,-3.35,53.56,179.93],"hull":4,"edges":[0,2,2,4,4,6,0,6],"width":202,"height":414}},"front_ef_24":{"front_ef_9":{"type":"mesh","uvs":[1,1,0,1,0,0,1,0],"triangles":[1,2,3,1,3,0],"vertices":[296.28,125.52,428.83,-247.64,88.65,-368.47,-43.9,4.69],"hull":4,"edges":[0,2,2,4,4,6,0,6],"width":396,"height":361}},"front_ef_25":{"front_ef_10":{"type":"mesh","uvs":[1,1,0,1,0,0,1,0],"triangles":[1,2,3,1,3,0],"vertices":[172.11,196.08,498.7,-125.01,305.91,-321.11,-20.69,-0.02],"hull":4,"edges":[0,2,2,4,4,6,0,6],"width":458,"height":275}},"front_ef_26":{"front_ef_11":{"type":"mesh","uvs":[1,1,0,1,0,0,1,0],"triangles":[1,2,3,1,3,0],"vertices":[2.12,62.77,228.07,-8.78,204.82,-82.18,-21.12,-10.63],"hull":4,"edges":[0,2,2,4,4,6,0,6],"width":237,"height":77}},"front_ef_27":{"front_ef_12":{"type":"mesh","uvs":[1,1,0,1,0,0,1,0],"triangles":[1,2,3,1,3,0],"vertices":[158.16,249,1058.08,-422.77,875.63,-667.18,-24.29,4.59],"hull":4,"edges":[0,2,2,4,4,6,0,6],"width":1123,"height":305}},"front_ef_28":{"front_ef_13":{"type":"mesh","uvs":[1,1,0,1,0,0,1,0],"triangles":[1,2,3,1,3,0],"vertices":[1.92,62,865.84,-120.55,812.5,-372.98,-51.42,-190.42],"hull":4,"edges":[0,2,2,4,4,6,0,6],"width":883,"height":258}},"front_ef_29":{"front_ef_14":{"type":"mesh","uvs":[1,1,0,1,0,0,1,0],"triangles":[1,2,3,1,3,0],"vertices":[-16.35,7.44,282.52,144.99,348.99,0.55,50.12,-137],"hull":4,"edges":[0,2,2,4,4,6,0,6],"width":329,"height":159}},"front_ef_3":{"front_ef_3":{"type":"mesh","uvs":[1,1,0,1,0,0,1,0],"triangles":[1,2,3,1,3,0],"vertices":[-18.85,-8.06,51.67,128.85,273.03,14.81,202.5,-122.09],"hull":4,"edges":[0,2,2,4,4,6,0,6],"width":154,"height":249}},"front_ef_30":{"front_ef_15":{"type":"mesh","uvs":[1,1,0,1,0,0,1,0],"triangles":[1,2,3,1,3,0],"vertices":[-15.68,58.76,1002.31,54.21,999.3,-621.78,-18.69,-617.23],"hull":4,"edges":[0,2,2,4,4,6,0,6],"width":1018,"height":676}},"front_ef_4":{"front_ef_4":{"type":"mesh","uvs":[1,1,0,1,0,0,1,0],"triangles":[1,2,3,1,3,0],"vertices":[-22.82,-7.07,83.46,168.23,381.89,-12.71,275.61,-188.01],"hull":4,"edges":[0,2,2,4,4,6,0,6],"width":205,"height":349}},"front_ef_5":{"front_ef_5":{"type":"mesh","uvs":[1,1,0,1,0,0,1,0],"triangles":[1,2,3,1,3,0],"vertices":[-29.62,0.06,233.01,231.42,496.1,-67.22,233.47,-298.58],"hull":4,"edges":[0,2,2,4,4,6,0,6],"width":350,"height":398}},"front_ef_6":{"front_ef_6":{"type":"mesh","uvs":[1,1,0,1,0,0,1,0],"triangles":[1,2,3,1,3,0],"vertices":[12.23,-71.06,-22.36,7.68,176.32,94.95,210.91,16.21],"hull":4,"edges":[0,2,2,4,4,6,0,6],"width":86,"height":217}},"front_ef_7":{"front_ef_7":{"type":"mesh","uvs":[1,1,0,1,0,0,1,0],"triangles":[1,2,3,1,3,0],"vertices":[135.54,-101.4,-29.5,-22.35,88,222.97,253.05,143.91],"hull":4,"edges":[0,2,2,4,4,6,0,6],"width":183,"height":272}},"front_ef_8":{"front_ef_8":{"type":"mesh","uvs":[1,1,0,1,0,0,1,0],"triangles":[1,2,3,1,3,0],"vertices":[429.19,5.86,344.26,-177.42,-31.37,-3.35,53.56,179.93],"hull":4,"edges":[0,2,2,4,4,6,0,6],"width":202,"height":414}},"front_ef_9":{"front_ef_9":{"type":"mesh","uvs":[1,1,0,1,0,0,1,0],"triangles":[1,2,3,1,3,0],"vertices":[296.28,125.52,428.83,-247.64,88.65,-368.47,-43.9,4.69],"hull":4,"edges":[0,2,2,4,4,6,0,6],"width":396,"height":361}},"purple_1":{"purple_1":{"x":0.7,"y":-0.2,"width":33,"height":33}},"purple_2":{"purple_2":{"x":0.47,"y":1.19,"width":47,"height":47}},"purple_3":{"purple_3":{"x":1.2,"y":1.18,"width":74,"height":73}},"purple_4":{"purple_4":{"x":0.72,"y":0.44,"width":54,"height":54}},"purple_5":{"purple_5":{"x":0.7,"y":0.29,"width":46,"height":46}},"purple_6":{"purple_6":{"x":2.97,"y":0.67,"width":51,"height":51}},"purple_7":{"purple_7":{"x":-0.38,"y":-0.36,"width":59,"height":58}},"purple_8":{"purple_8":{"x":0.16,"y":0.79,"width":74,"height":74}},"purple_9":{"purple_9":{"x":0.12,"y":1.14,"rotation":0.36,"width":53,"height":54}},"shadow":{"shadow":{"x":-114.22,"y":-135.38,"width":1152,"height":1729}},"shadow2":{"shadow":{"x":-114.22,"y":-135.38,"width":1152,"height":1729}},"shadow3":{"shadow":{"x":-114.22,"y":-135.38,"width":1152,"height":1729}},"shadow4":{"shadow":{"x":-114.22,"y":-135.38,"width":1152,"height":1729}},"weapon_line_1":{"weapon_line_1":{"x":816.27,"y":-3.33,"rotation":-85.63,"width":70,"height":770}},"weapon_line_2":{"weapon_line_2":{"type":"mesh","uvs":[1,1,0,1,0,0,1,0],"triangles":[1,2,3,1,3,0],"vertices":[246.17,-413.23,-1.37,0.34,758,454.86,1005.54,41.28],"hull":4,"edges":[0,2,2,4,4,6,0,6],"width":482,"height":885}},"weapon_line_3":{"weapon_line_3":{"type":"mesh","uvs":[1,1,0,1,0,0,1,0],"triangles":[1,2,3,1,3,0],"vertices":[0.04,1.41,652.04,621.81,1275.19,-33.1,623.19,-653.49],"hull":4,"edges":[0,2,2,4,4,6,0,6],"width":900,"height":904}},"weapon_line_4":{"weapon_line_4":{"type":"mesh","uvs":[1,1,0,1,0,0,1,0],"triangles":[1,2,3,1,3,0],"vertices":[411.62,-248.88,-3.25,-1.55,158.56,269.87,573.43,22.55],"hull":4,"edges":[0,2,2,4,4,6,0,6],"width":483,"height":316}},"weapon_line_5":{"weapon_line_5":{"type":"mesh","uvs":[1,1,0,1,0,0,1,0],"triangles":[1,2,3,1,3,0],"vertices":[-1.36,2.85,893.7,114.53,917.34,-75,22.28,-186.68],"hull":4,"edges":[0,2,2,4,4,6,0,6],"width":902,"height":191}},"weapon_line_6":{"weapon_line_6":{"type":"mesh","uvs":[1,1,0,1,0,0,1,0],"triangles":[1,2,3,1,3,0],"vertices":[536.56,10.21,108.7,-211.73,-0.89,-0.46,426.98,221.48],"hull":4,"edges":[0,2,2,4,4,6,0,6],"width":482,"height":238}},"weapon_line_7":{"weapon_line_7":{"type":"mesh","uvs":[1,1,0,1,0,0,1,0],"triangles":[1,2,3,1,3,0],"vertices":[824.8,201.28,877.16,-15.48,50.92,-215.06,-1.44,1.71],"hull":4,"edges":[0,2,2,4,4,6,0,6],"width":223,"height":850}}}}],"animations":{"animation":{"slots":{"back_ef_1_1":{"color":[{"color":"7e7e7e00"},{"time":0.5,"color":"7e7e7eff","curve":"stepped"},{"time":1,"color":"7e7e7eff"},{"time":1.4667,"color":"7e7e7e00"}]},"back_ef_1_2":{"color":[{"color":"2b2b2b00"},{"time":0.5,"color":"2b2b2bff","curve":"stepped"},{"time":1,"color":"2b2b2bff"},{"time":1.4667,"color":"2b2b2b00"}]},"back_ef_1_3":{"color":[{"color":"2b2b2b00","curve":"stepped"},{"time":0.8333,"color":"2b2b2b00"},{"time":1.3333,"color":"2b2b2bff","curve":"stepped"},{"time":1.8333,"color":"2b2b2bff"},{"time":2.3,"color":"2b2b2b00"}]},"back_ef_1_4":{"color":[{"color":"7e7e7e00","curve":"stepped"},{"time":0.8333,"color":"7e7e7e00"},{"time":1.3333,"color":"7e7e7eff","curve":"stepped"},{"time":1.8333,"color":"7e7e7eff"},{"time":2.3,"color":"7e7e7e00"}]},"back_ef_1_5":{"color":[{"color":"2b2b2bff"},{"time":0.4667,"color":"2b2b2b00","curve":"stepped"},{"time":1.6667,"color":"2b2b2b00"},{"time":2.1667,"color":"2b2b2bff"}]},"back_ef_1_6":{"color":[{"color":"7e7e7eff"},{"time":0.4667,"color":"7e7e7e00","curve":"stepped"},{"time":1.6667,"color":"7e7e7e00"},{"time":2.1667,"color":"7e7e7eff"}]},"back_ef_2_1":{"color":[{"color":"40404000"},{"time":0.5,"color":"404040ff","curve":"stepped"},{"time":1,"color":"404040ff"},{"time":1.4667,"color":"40404000"}]},"back_ef_2_2":{"color":[{"color":"99999900"},{"time":0.5,"color":"999999ff","curve":"stepped"},{"time":1,"color":"999999ff"},{"time":1.4667,"color":"99999900"}]},"back_ef_2_3":{"color":[{"color":"99999900","curve":"stepped"},{"time":0.8333,"color":"99999900"},{"time":1.3333,"color":"999999ff","curve":"stepped"},{"time":1.8333,"color":"999999ff"},{"time":2.3,"color":"99999900"}]},"back_ef_2_4":{"color":[{"color":"40404000","curve":"stepped"},{"time":0.8333,"color":"40404000"},{"time":1.3333,"color":"404040ff","curve":"stepped"},{"time":1.8333,"color":"404040ff"},{"time":2.3,"color":"40404000"}]},"back_ef_2_5":{"color":[{"color":"999999ff"},{"time":0.4667,"color":"99999900","curve":"stepped"},{"time":1.6667,"color":"99999900"},{"time":2.1667,"color":"999999ff"}]},"back_ef_2_6":{"color":[{"color":"404040ff"},{"time":0.4667,"color":"40404000","curve":"stepped"},{"time":1.6667,"color":"40404000"},{"time":2.1667,"color":"404040ff"}]},"back_ef_3_1":{"color":[{"color":"79797900","curve":"stepped"},{"time":0.3333,"color":"79797900"},{"time":0.8333,"color":"797979ff","curve":"stepped"},{"time":1.3333,"color":"797979ff"},{"time":1.8,"color":"79797900"}]},"back_ef_3_2":{"color":[{"color":"81818100","curve":"stepped"},{"time":0.3333,"color":"81818100"},{"time":0.8333,"color":"818181ff","curve":"stepped"},{"time":1.3333,"color":"818181ff"},{"time":1.8,"color":"81818100"}]},"back_ef_3_3":{"color":[{"color":"81818100","curve":"stepped"},{"time":1.1667,"color":"81818100"},{"time":1.6667,"color":"818181ff","curve":"stepped"},{"time":2.1667,"color":"818181ff"},{"time":2.6333,"color":"81818100"}]},"back_ef_3_4":{"color":[{"color":"79797900","curve":"stepped"},{"time":1.1667,"color":"79797900"},{"time":1.6667,"color":"797979ff","curve":"stepped"},{"time":2.1667,"color":"797979ff"},{"time":2.6333,"color":"79797900"}]},"back_ef_3_5":{"color":[{"color":"818181ff","curve":"stepped"},{"time":0.3333,"color":"818181ff"},{"time":0.8,"color":"81818100","curve":"stepped"},{"time":2,"color":"81818100"},{"time":2.5,"color":"818181ff"}]},"back_ef_3_6":{"color":[{"color":"797979ff","curve":"stepped"},{"time":0.3333,"color":"797979ff"},{"time":0.8,"color":"79797900","curve":"stepped"},{"time":2,"color":"79797900"},{"time":2.5,"color":"797979ff"}]},"flare":{"color":[{"color":"ffffff00"},{"time":0.3333,"color":"ffffffff","curve":"stepped"},{"time":0.8,"color":"ffffffff"},{"time":1.3,"color":"ffffff00","curve":"stepped"},{"time":1.3333,"color":"ffffff00"},{"time":1.6667,"color":"ffffffff","curve":"stepped"},{"time":2.1333,"color":"ffffffff"},{"time":2.6667,"color":"ffffff00"}]},"flower_1":{"color":[{"color":"ffffff00"},{"time":0.4667,"color":"ffffffff"},{"time":0.8333,"color":"ffffff00","curve":"stepped"},{"time":1.3333,"color":"ffffff00"},{"time":1.8,"color":"ffffffff"},{"time":2.1667,"color":"ffffff00"}]},"flower_2":{"color":[{"time":0.0667,"color":"ffffffff"},{"time":0.3667,"color":"ffffff00","curve":"stepped"},{"time":0.8333,"color":"ffffff00"},{"time":1.1667,"color":"ffffffff","curve":"stepped"},{"time":1.4,"color":"ffffffff"},{"time":1.7,"color":"ffffff00","curve":"stepped"},{"time":2.1667,"color":"ffffff00"},{"time":2.5,"color":"ffffffff"}]},"flower_3":{"color":[{"color":"ffffff00","curve":"stepped"},{"time":0.2333,"color":"ffffff00"},{"time":0.4,"color":"ffffffff","curve":"stepped"},{"time":0.8667,"color":"ffffffff"},{"time":1.3333,"color":"ffffff00","curve":"stepped"},{"time":1.5667,"color":"ffffff00"},{"time":1.7333,"color":"ffffffff","curve":"stepped"},{"time":2.2,"color":"ffffffff"},{"time":2.6667,"color":"ffffff00"}]},"flower_4":{"color":[{"color":"ffffff00","curve":"stepped"},{"time":0.3333,"color":"ffffff00"},{"time":0.7333,"color":"ffffffff","curve":"stepped"},{"time":0.8333,"color":"ffffffff"},{"time":1.3333,"color":"ffffff00","curve":"stepped"},{"time":1.6667,"color":"ffffff00"},{"time":2.0667,"color":"ffffffff","curve":"stepped"},{"time":2.1667,"color":"ffffffff"},{"time":2.6667,"color":"ffffff00"}]},"flower_5":{"color":[{"color":"ffffffbf"},{"time":0.1667,"color":"ffffff00","curve":"stepped"},{"time":0.5,"color":"ffffff00"},{"time":0.8,"color":"ffffffbf","curve":"stepped"},{"time":1.3333,"color":"ffffffbf"},{"time":1.5,"color":"ffffff00","curve":"stepped"},{"time":1.8333,"color":"ffffff00"},{"time":2.1333,"color":"ffffffbf"}]},"flower_6":{"color":[{"color":"ffffff00"},{"time":0.2667,"color":"ffffffff","curve":"stepped"},{"time":0.8667,"color":"ffffffff"},{"time":1.3333,"color":"ffffff00"},{"time":1.6,"color":"ffffffff","curve":"stepped"},{"time":2.2,"color":"ffffffff"},{"time":2.6667,"color":"ffffff00"}]},"flower_7":{"color":[{"time":0.1,"color":"ffffffff"},{"time":0.5667,"color":"ffffff00","curve":"stepped"},{"time":0.6,"color":"ffffff00"},{"time":1,"color":"ffffffff","curve":"stepped"},{"time":1.4333,"color":"ffffffff"},{"time":1.9,"color":"ffffff00","curve":"stepped"},{"time":1.9333,"color":"ffffff00"},{"time":2.3333,"color":"ffffffff"}]},"flower_8":{"color":[{"time":0.4,"color":"ffffffff"},{"time":0.6333,"color":"ffffff00","curve":"stepped"},{"time":0.6667,"color":"ffffff00"},{"time":1,"color":"ffffffff","curve":"stepped"},{"time":1.7333,"color":"ffffffff"},{"time":1.9667,"color":"ffffff00","curve":"stepped"},{"time":2,"color":"ffffff00"},{"time":2.3333,"color":"ffffffff"}]},"flower_9":{"color":[{"color":"ffffff00"},{"time":0.3667,"color":"ffffffff","curve":"stepped"},{"time":0.9,"color":"ffffffff"},{"time":1.3333,"color":"ffffff00"},{"time":1.7,"color":"ffffffff","curve":"stepped"},{"time":2.2333,"color":"ffffffff"},{"time":2.6667,"color":"ffffff00"}]},"flower_10":{"color":[{"color":"ffffff46"},{"time":0.2333,"color":"ffffff00","curve":"stepped"},{"time":0.2667,"color":"ffffff00"},{"time":0.6667,"color":"ffffffff"},{"time":1.3333,"color":"ffffff46"},{"time":1.5667,"color":"ffffff00","curve":"stepped"},{"time":1.6,"color":"ffffff00"},{"time":2,"color":"ffffffff"},{"time":2.6667,"color":"ffffff46"}]},"flower_11":{"color":[{"time":0.5,"color":"ffffffff"},{"time":0.9,"color":"ffffff00","curve":"stepped"},{"time":0.9333,"color":"ffffff00"},{"time":1.2667,"color":"ffffffff","curve":"stepped"},{"time":1.8333,"color":"ffffffff"},{"time":2.2333,"color":"ffffff00","curve":"stepped"},{"time":2.2667,"color":"ffffff00"},{"time":2.6,"color":"ffffffff"}]},"flower_12":{"color":[{"time":0.8333,"color":"ffffffff"},{"time":1.0667,"color":"ffffff00","curve":"stepped"},{"time":1.1,"color":"ffffff00"},{"time":1.3333,"color":"ffffffff","curve":"stepped"},{"time":2.1667,"color":"ffffffff"},{"time":2.4,"color":"ffffff00","curve":"stepped"},{"time":2.4333,"color":"ffffff00"},{"time":2.6667,"color":"ffffffff"}]},"flower_13":{"color":[{"color":"ffffff66"},{"time":0.2333,"color":"ffffffff","curve":"stepped"},{"time":0.6667,"color":"ffffffff"},{"time":1.1333,"color":"ffffff00","curve":"stepped"},{"time":1.1667,"color":"ffffff00"},{"time":1.3333,"color":"ffffff66"},{"time":1.5667,"color":"ffffffff","curve":"stepped"},{"time":2,"color":"ffffffff"},{"time":2.4667,"color":"ffffff00","curve":"stepped"},{"time":2.5,"color":"ffffff00"},{"time":2.6667,"color":"ffffff66"}]},"flower_14":{"color":[{"color":"ffffffff"},{"time":0.4667,"color":"ffffff00","curve":"stepped"},{"time":0.5,"color":"ffffff00"},{"time":0.8333,"color":"ffffffff","curve":"stepped"},{"time":1.3333,"color":"ffffffff"},{"time":1.8,"color":"ffffff00","curve":"stepped"},{"time":1.8333,"color":"ffffff00"},{"time":2.1667,"color":"ffffffff"}]},"flower_15":{"color":[{"color":"ffffffdb"},{"time":0.4,"color":"ffffff00","curve":"stepped"},{"time":0.4333,"color":"ffffff00"},{"time":0.8333,"color":"ffffffff","curve":"stepped"},{"time":1.2667,"color":"ffffffff"},{"time":1.3333,"color":"ffffffdb"},{"time":1.7333,"color":"ffffff00","curve":"stepped"},{"time":1.7667,"color":"ffffff00"},{"time":2.1667,"color":"ffffffff","curve":"stepped"},{"time":2.6,"color":"ffffffff"},{"time":2.6667,"color":"ffffffdb"}]},"front_ef_1":{"color":[{"color":"ffffff00","curve":"stepped"},{"time":0.5,"color":"ffffff00"},{"time":1,"color":"ffffffff","curve":"stepped"},{"time":1.5,"color":"ffffffff"},{"time":1.9667,"color":"ffffff00"}]},"front_ef_2":{"color":[{"color":"ffffff00"},{"time":0.5,"color":"ffffffff","curve":"stepped"},{"time":1,"color":"ffffffff"},{"time":1.4667,"color":"ffffff00"}]},"front_ef_3":{"color":[{"color":"ffffff48"},{"time":0.1333,"color":"ffffff00","curve":"stepped"},{"time":1.3333,"color":"ffffff00"},{"time":1.8333,"color":"ffffffff","curve":"stepped"},{"time":2.3333,"color":"ffffffff"},{"time":2.6667,"color":"ffffff48"}]},"front_ef_4":{"color":[{"time":0.1667,"color":"ffffffff"},{"time":0.6333,"color":"ffffff00","curve":"stepped"},{"time":1.8333,"color":"ffffff00"},{"time":2.3333,"color":"ffffffff"}]},"front_ef_5":{"color":[{"color":"ffffff00"},{"time":0.5,"color":"ffffffff","curve":"stepped"},{"time":1,"color":"ffffffff"},{"time":1.4667,"color":"ffffff00","curve":"stepped"},{"time":1.5,"color":"ffffff00"}]},"front_ef_6":{"color":[{"color":"ffffff00"},{"time":0.4667,"color":"ffffffff","curve":"stepped"},{"time":1,"color":"ffffffff"},{"time":1.4667,"color":"ffffff00"}]},"front_ef_7":{"color":[{"color":"ffffff00","curve":"stepped"},{"time":1.1,"color":"ffffff00"},{"time":1.6,"color":"ffffffff","curve":"stepped"},{"time":2.1,"color":"ffffffff"},{"time":2.5667,"color":"ffffff00"}]},"front_ef_8":{"color":[{"color":"ffffff00","curve":"stepped"},{"time":0.4,"color":"ffffff00"},{"time":0.9,"color":"ffffffff","curve":"stepped"},{"time":1.4,"color":"ffffffff"},{"time":1.8667,"color":"ffffff11","curve":"stepped"},{"time":1.9,"color":"ffffff00"}]},"front_ef_9":{"color":[{"color":"ffffff48"},{"time":0.1333,"color":"ffffff00","curve":"stepped"},{"time":1.3333,"color":"ffffff00"},{"time":1.6667,"color":"ffffffff","curve":"stepped"},{"time":2.3333,"color":"ffffffff"},{"time":2.6667,"color":"ffffff48"}]},"front_ef_10":{"color":[{"color":"ffffff00"},{"time":0.4667,"color":"ffffffff","curve":"stepped"},{"time":1,"color":"ffffffff"},{"time":1.4667,"color":"ffffff00"}]},"front_ef_11":{"color":[{"color":"ffffff00"},{"time":0.5,"color":"ffffffff","curve":"stepped"},{"time":0.9667,"color":"ffffffff"},{"time":1.4667,"color":"ffffff00"}]},"front_ef_12":{"color":[{"time":0.1,"color":"ffffffff"},{"time":0.5667,"color":"ffffff00","curve":"stepped"},{"time":1.7667,"color":"ffffff00"},{"time":2.2667,"color":"ffffffff"}]},"front_ef_13":{"color":[{"color":"ffffff00","curve":"stepped"},{"time":0.3667,"color":"ffffff00"},{"time":0.8667,"color":"ffffffff","curve":"stepped"},{"time":1.3667,"color":"ffffffff"},{"time":1.8333,"color":"ffffff00"}]},"front_ef_14":{"color":[{"color":"ffffff00"},{"time":0.5,"color":"ffffffff","curve":"stepped"},{"time":1,"color":"ffffffff"},{"time":1.4667,"color":"ffffff00"}]},"front_ef_15":{"color":[{"time":0.5,"color":"ffffffff"},{"time":0.9667,"color":"ffffff00","curve":"stepped"},{"time":2.1667,"color":"ffffff00"},{"time":2.6667,"color":"ffffffff"}]},"front_ef_16":{"color":[{"time":0.1667,"color":"ffffffff"},{"time":0.5,"color":"ffffff49"},{"time":0.6333,"color":"ffffff00","curve":"stepped"},{"time":1.8333,"color":"ffffff00"},{"time":2.3333,"color":"ffffffff"}]},"front_ef_17":{"color":[{"color":"ffffff48"},{"time":0.1333,"color":"ffffff00","curve":"stepped"},{"time":1.3333,"color":"ffffff00"},{"time":1.8333,"color":"ffffffff","curve":"stepped"},{"time":2.3333,"color":"ffffffff"},{"time":2.6667,"color":"ffffff48"}]},"front_ef_18":{"color":[{"color":"ffffff00"},{"time":0.5,"color":"ffffffff","curve":"stepped"},{"time":1,"color":"ffffffff"},{"time":1.3333,"color":"ffffff48"},{"time":1.4667,"color":"ffffff00"}]},"front_ef_19":{"color":[{"color":"ffffff00","curve":"stepped"},{"time":0.5,"color":"ffffff00"},{"time":1,"color":"ffffffff","curve":"stepped"},{"time":1.5,"color":"ffffffff"},{"time":1.8333,"color":"ffffff49"},{"time":1.9667,"color":"ffffff00"}]},"front_ef_20":{"color":[{"color":"ffffff48"},{"time":0.1333,"color":"ffffff00","curve":"stepped"},{"time":0.1667,"color":"ffffff00","curve":"stepped"},{"time":1.3333,"color":"ffffff00"},{"time":1.8333,"color":"ffffffff","curve":"stepped"},{"time":2.3333,"color":"ffffffff"},{"time":2.6667,"color":"ffffff48"}]},"front_ef_21":{"color":[{"color":"ffffff49"},{"time":0.1333,"color":"ffffff00","curve":"stepped"},{"time":1.3333,"color":"ffffff00"},{"time":1.8,"color":"ffffffff","curve":"stepped"},{"time":2.3333,"color":"ffffffff"},{"time":2.6667,"color":"ffffff49"}]},"front_ef_22":{"color":[{"color":"ffffff77"},{"time":0.2667,"color":"ffffffff","curve":"stepped"},{"time":0.7667,"color":"ffffffff"},{"time":1.1,"color":"ffffff48"},{"time":1.2333,"color":"ffffff00","curve":"stepped"},{"time":2.4333,"color":"ffffff00"},{"time":2.6667,"color":"ffffff77"}]},"front_ef_23":{"color":[{"time":0.0667,"color":"ffffffff"},{"time":0.4,"color":"ffffff55"},{"time":0.5333,"color":"ffffff11","curve":"stepped"},{"time":0.5667,"color":"ffffff00","curve":"stepped"},{"time":1.7333,"color":"ffffff00"},{"time":2.0333,"color":"ffffff99"},{"time":2.2333,"color":"ffffffff"}]},"front_ef_24":{"color":[{"color":"ffffff00"},{"time":0.3333,"color":"ffffffff","curve":"stepped"},{"time":1,"color":"ffffffff"},{"time":1.3333,"color":"ffffff48"},{"time":1.4667,"color":"ffffff00"}]},"front_ef_25":{"color":[{"color":"ffffff48"},{"time":0.1333,"color":"ffffff00","curve":"stepped"},{"time":1.3333,"color":"ffffff00"},{"time":1.8,"color":"ffffffff","curve":"stepped"},{"time":2.3333,"color":"ffffffff"},{"time":2.6667,"color":"ffffff48"}]},"front_ef_26":{"color":[{"color":"ffffff43"},{"time":0.1333,"color":"ffffff00","curve":"stepped"},{"time":1.3333,"color":"ffffff00"},{"time":1.8333,"color":"ffffffff","curve":"stepped"},{"time":2.3,"color":"ffffffff"},{"time":2.6667,"color":"ffffff43"}]},"front_ef_27":{"color":[{"color":"ffffff00","curve":"stepped"},{"time":0.4333,"color":"ffffff00"},{"time":0.9333,"color":"ffffffff","curve":"stepped"},{"time":1.4333,"color":"ffffffff"},{"time":1.7667,"color":"ffffff48"},{"time":1.9,"color":"ffffff00"}]},"front_ef_28":{"color":[{"time":0.0333,"color":"ffffffff"},{"time":0.3667,"color":"ffffff49"},{"time":0.5,"color":"ffffff00","curve":"stepped"},{"time":1.7,"color":"ffffff00"},{"time":2.2,"color":"ffffffff"}]},"front_ef_29":{"color":[{"color":"ffffff48"},{"time":0.1333,"color":"ffffff00","curve":"stepped"},{"time":1.3333,"color":"ffffff00"},{"time":1.8333,"color":"ffffffff","curve":"stepped"},{"time":2.3333,"color":"ffffffff"},{"time":2.6667,"color":"ffffff48"}]},"front_ef_30":{"color":[{"color":"ffffff00","curve":"stepped"},{"time":0.8333,"color":"ffffff00"},{"time":1.3333,"color":"ffffffff","curve":"stepped"},{"time":1.8333,"color":"ffffffff"},{"time":2.1667,"color":"ffffff48"},{"time":2.3,"color":"ffffff00"}]},"purple_1":{"color":[{"color":"ffffff00"},{"time":0.6667,"color":"ffffffff","curve":"stepped"},{"time":1.3333,"color":"ffffffff"},{"time":2.3333,"color":"ffffff00"}]},"purple_2":{"color":[{"color":"ffffffff"},{"time":0.5667,"color":"ffffff00","curve":"stepped"},{"time":1.7667,"color":"ffffff00"},{"time":2.3,"color":"ffffffff"}]},"purple_3":{"color":[{"color":"ffffff00","curve":"stepped"},{"time":0.3333,"color":"ffffff00"},{"time":1,"color":"ffffffff","curve":"stepped"},{"time":1.3333,"color":"ffffffff"},{"time":1.8,"color":"ffffff00"}]},"purple_4":{"color":[{"color":"ffffff8e","curve":0.25,"c3":0.75},{"time":0.1333,"color":"ffffff00","curve":"stepped"},{"time":1.3333,"color":"ffffff00","curve":0.25,"c3":0.75},{"time":1.9333,"color":"ffffffff","curve":"stepped"},{"time":2.3,"color":"ffffffff","curve":0.25,"c3":0.75},{"time":2.6667,"color":"ffffff8e"}]},"purple_5":{"color":[{"time":0.2667,"color":"ffffffff"},{"time":1.3333,"color":"ffffff00","curve":"stepped"},{"time":2,"color":"ffffff00"},{"time":2.5,"color":"ffffffff"}]},"purple_6":{"color":[{"color":"ffffff00"},{"time":0.6667,"color":"ffffffff","curve":"stepped"},{"time":1.6667,"color":"ffffffff"},{"time":2.6667,"color":"ffffff00"}]},"purple_7":{"color":[{"color":"ffffff99"},{"time":0.5,"color":"ffffff00","curve":"stepped"},{"time":1.1667,"color":"ffffff00"},{"time":1.8333,"color":"ffffffff","curve":"stepped"},{"time":2.3333,"color":"ffffffff"},{"time":2.6667,"color":"ffffff99"}]},"purple_8":{"color":[{"color":"ffffffbf"},{"time":0.1667,"color":"ffffffff","curve":"stepped"},{"time":0.8333,"color":"ffffffff"},{"time":1.3333,"color":"ffffff00","curve":"stepped"},{"time":2.1333,"color":"ffffff00"},{"time":2.1667,"color":"ffffff00"},{"time":2.6667,"color":"ffffffbf"}]},"purple_9":{"color":[{"color":"ffffff00"},{"time":0.6667,"color":"ffffffff","curve":"stepped"},{"time":1.5,"color":"ffffffff"},{"time":2.6667,"color":"ffffff00"}]},"shadow":{"color":[{"color":"39393900"},{"time":1.3333,"color":"3939397c"},{"time":2.6333,"color":"39393900"}]},"shadow2":{"color":[{"color":"3939397c"},{"time":1.3,"color":"39393900","curve":"stepped"},{"time":1.3333,"color":"39393900"},{"time":2.6667,"color":"3939397c"}]},"shadow3":{"color":[{"color":"39393900"},{"time":1.3333,"color":"3939397c"},{"time":2.6333,"color":"39393900"}]},"shadow4":{"color":[{"color":"3939397c"},{"time":1.3,"color":"39393900","curve":"stepped"},{"time":1.3333,"color":"39393900"},{"time":2.6667,"color":"3939397c"}]},"weapon_line_1":{"color":[{"color":"ffffff00"},{"time":0.2,"color":"ffffffff","curve":"stepped"},{"time":0.4333,"color":"ffffffff"},{"time":0.6333,"color":"ffffff00","curve":"stepped"},{"time":0.6667,"color":"ffffff00"},{"time":0.9,"color":"ffffffff","curve":"stepped"},{"time":1.1333,"color":"ffffffff"},{"time":1.3,"color":"ffffff00","curve":"stepped"},{"time":1.3333,"color":"ffffff00"},{"time":1.5333,"color":"ffffffff","curve":"stepped"},{"time":1.7667,"color":"ffffffff"},{"time":1.9667,"color":"ffffff00","curve":"stepped"},{"time":2,"color":"ffffff00"},{"time":2.2333,"color":"ffffffff","curve":"stepped"},{"time":2.4667,"color":"ffffffff"},{"time":2.6333,"color":"ffffff00"}]},"weapon_line_2":{"color":[{"time":0.1,"color":"ffffffff"},{"time":0.3667,"color":"ffffff00","curve":"stepped"},{"time":0.4,"color":"ffffff00"},{"time":0.7,"color":"ffffffff","curve":"stepped"},{"time":0.9667,"color":"ffffffff"},{"time":1.2667,"color":"ffffff00","curve":"stepped"},{"time":1.3,"color":"ffffff00"},{"time":1.6,"color":"ffffffff","curve":"stepped"},{"time":1.8667,"color":"ffffffff"},{"time":2.1667,"color":"ffffff00","curve":"stepped"},{"time":2.2,"color":"ffffff00"},{"time":2.5,"color":"ffffffff"}]},"weapon_line_3":{"color":[{"color":"ffffff00"},{"time":0.3,"color":"ffffffff","curve":"stepped"},{"time":0.5333,"color":"ffffffff"},{"time":0.8667,"color":"ffffff00","curve":"stepped"},{"time":0.9,"color":"ffffff00"},{"time":1.2,"color":"ffffffff","curve":"stepped"},{"time":1.4,"color":"ffffffff"},{"time":1.7667,"color":"ffffff00","curve":"stepped"},{"time":1.8,"color":"ffffff00"},{"time":2.1,"color":"ffffffff","curve":"stepped"},{"time":2.3333,"color":"ffffffff"},{"time":2.6333,"color":"ffffff00"}]},"weapon_line_4":{"color":[{"color":"ffffff54"},{"time":0.1,"color":"ffffff00","curve":"stepped"},{"time":0.1333,"color":"ffffff00"},{"time":0.4667,"color":"ffffffff","curve":"stepped"},{"time":0.7,"color":"ffffffff"},{"time":0.9667,"color":"ffffff00","curve":"stepped"},{"time":1,"color":"ffffff00"},{"time":1.3333,"color":"ffffffff","curve":"stepped"},{"time":1.5667,"color":"ffffffff"},{"time":1.8667,"color":"ffffff00","curve":"stepped"},{"time":1.9,"color":"ffffff00"},{"time":2.2333,"color":"ffffffff","curve":"stepped"},{"time":2.4667,"color":"ffffffff"},{"time":2.6667,"color":"ffffff54"}]},"weapon_line_5":{"color":[{"color":"ffffff7f"},{"time":0.1,"color":"ffffff00","curve":"stepped"},{"time":0.1333,"color":"ffffff00"},{"time":0.4333,"color":"ffffffff","curve":"stepped"},{"time":0.7667,"color":"ffffffff"},{"time":1,"color":"ffffff00","curve":"stepped"},{"time":1.0333,"color":"ffffff00"},{"time":1.3333,"color":"ffffffff","curve":"stepped"},{"time":1.6667,"color":"ffffffff"},{"time":1.9,"color":"ffffff00","curve":"stepped"},{"time":1.9333,"color":"ffffff00"},{"time":2.2333,"color":"ffffffff","curve":"stepped"},{"time":2.5667,"color":"ffffffff"},{"time":2.6667,"color":"ffffff7f"}]},"weapon_line_6":{"color":[{"color":"ffffff00","curve":"stepped"},{"time":0.0333,"color":"ffffff00"},{"time":0.3,"color":"ffffffff","curve":"stepped"},{"time":0.6,"color":"ffffffff"},{"time":0.8667,"color":"ffffff00","curve":"stepped"},{"time":0.9,"color":"ffffff00"},{"time":1.1667,"color":"ffffffff","curve":"stepped"},{"time":1.4667,"color":"ffffffff"},{"time":1.7667,"color":"ffffff00","curve":"stepped"},{"time":1.8,"color":"ffffff00"},{"time":2.0667,"color":"ffffffff","curve":"stepped"},{"time":2.3667,"color":"ffffffff"},{"time":2.6667,"color":"ffffff00"}]},"weapon_line_7":{"color":[{"color":"ffffffaa"},{"time":0.1,"color":"ffffffff","curve":"stepped"},{"time":0.3333,"color":"ffffffff"},{"time":0.6333,"color":"ffffff00","curve":"stepped"},{"time":0.6667,"color":"ffffff00"},{"time":0.9667,"color":"ffffffff","curve":"stepped"},{"time":1.2,"color":"ffffffff"},{"time":1.5333,"color":"ffffff00","curve":"stepped"},{"time":1.5667,"color":"ffffff00"},{"time":1.8667,"color":"ffffffff","curve":"stepped"},{"time":2.1,"color":"ffffffff"},{"time":2.4333,"color":"ffffff00","curve":"stepped"},{"time":2.4667,"color":"ffffff00"},{"time":2.6667,"color":"ffffffaa"}]}},"bones":{"back_ef_1_1":{"rotate":[{},{"time":1.4667,"angle":15.42,"curve":"stepped"},{"time":1.5}],"translate":[{},{"time":1.4667,"x":-146.7,"y":37.88,"curve":"stepped"},{"time":1.5}]},"back_ef_2_1":{"rotate":[{},{"time":1.4667,"angle":50.72,"curve":"stepped"},{"time":1.5}],"translate":[{},{"time":1.4667,"x":-3.02,"y":159.9,"curve":"stepped"},{"time":1.5}]},"back_ef_3_1":{"rotate":[{"time":0.3333},{"time":1.8,"angle":28.92,"curve":"stepped"},{"time":1.8333}],"translate":[{"time":0.3333},{"time":1.8,"x":-59.99,"y":133.49,"curve":"stepped"},{"time":1.8333}],"shear":[{"time":0.3333},{"time":1.8,"x":4.28,"y":15.31,"curve":"stepped"},{"time":1.8333}]},"flower_1":{"rotate":[{},{"time":1.3,"angle":-155.75},{"time":1.3333},{"time":2.6333,"angle":-155.75},{"time":2.6667}],"translate":[{"x":-101.86,"y":-293.43},{"time":1.3,"x":-236.35,"y":-28.91},{"time":1.3333,"x":-101.86,"y":-293.43},{"time":2.6333,"x":-236.35,"y":-28.91},{"time":2.6667}]},"flower_2":{"rotate":[{"angle":60.73},{"time":0.8,"angle":154.31},{"time":0.8333},{"time":1.3333,"angle":60.73},{"time":2.1333,"angle":154.31},{"time":2.1667},{"time":2.6667,"angle":60.73}],"translate":[{"x":-192.74,"y":65.37},{"time":0.8,"x":-307.58,"y":288.25},{"time":0.8333,"x":-120.09,"y":-75.63},{"time":1.3333,"x":-192.74,"y":65.37},{"time":2.1333,"x":-307.58,"y":288.25},{"time":2.1667,"x":-120.09,"y":-75.63},{"time":2.6667,"x":-192.74,"y":65.37}]},"flower_3":{"rotate":[{"time":1.5667},{"time":2.6667,"angle":117.21}],"translate":[{"x":-129.91,"y":-63.82,"curve":"stepped"},{"time":1.5667,"x":-129.91,"y":-63.82},{"time":2.6667,"x":-274.9,"y":137}]},"flower_6":{"rotate":[{"time":1.3333},{"time":2.6667,"angle":-153.82}],"translate":[{"x":-91.66,"y":18.23,"curve":"stepped"},{"time":1.3333,"x":-91.66,"y":18.23},{"time":2.6667,"x":-217.71,"y":341.71}]},"flower_9":{"rotate":[{"time":1.3333},{"time":2.6667,"angle":-61.83}],"translate":[{"x":164.73,"y":-237.32,"curve":"stepped"},{"time":1.3333,"x":164.73,"y":-237.32},{"time":2.6667}]},"flower_11":{"rotate":[{"angle":-51.15},{"time":0.9,"angle":-168.38},{"time":0.9333},{"time":1.3333,"angle":-51.15},{"time":2.2333,"angle":-168.38},{"time":2.2667},{"time":2.6667,"angle":-51.15}],"translate":[{"x":313.5,"y":64.47},{"time":0.9,"x":179.19,"y":334.72},{"time":0.9333,"x":372.11,"y":-53.46},{"time":1.3333,"x":313.5,"y":64.47},{"time":2.2333,"x":179.19,"y":334.72},{"time":2.2667,"x":372.11,"y":-53.46},{"time":2.6667,"x":313.5,"y":64.47}]},"flower_12":{"rotate":[{"angle":-15.83},{"time":1.0667,"angle":-137.11},{"time":1.1,"angle":12.59},{"time":1.3333,"angle":-15.83},{"time":2.4,"angle":-137.11},{"time":2.4333,"angle":12.59},{"time":2.6667,"angle":-15.83}],"translate":[{"x":261.11,"y":-183.48},{"time":1.0667,"x":78.6,"y":191.11},{"time":1.1,"x":303.88,"y":-271.27},{"time":1.3333,"x":261.11,"y":-183.48},{"time":2.4,"x":78.6,"y":191.11},{"time":2.4333,"x":303.88,"y":-271.27},{"time":2.6667,"x":261.11,"y":-183.48}]},"weapon_line_1":{"translate":[{"x":-1.77,"y":-23.15},{"time":0.6333,"x":11.65,"y":152.49},{"time":0.6667,"x":-1.77,"y":-23.15},{"time":1.3,"x":11.65,"y":152.49},{"time":1.3333,"x":-1.77,"y":-23.15},{"time":1.9667,"x":11.65,"y":152.49},{"time":2,"x":-1.77,"y":-23.15},{"time":2.6333,"x":11.65,"y":152.49},{"time":2.6667,"x":-1.77,"y":-23.15}],"scale":[{"x":0.817,"y":0.972},{"time":0.6333,"y":0.656},{"time":0.6667,"x":0.817,"y":0.972},{"time":1.3,"y":0.656},{"time":1.3333,"x":0.817,"y":0.972},{"time":1.9667,"y":0.656},{"time":2,"x":0.817,"y":0.972},{"time":2.6333,"y":0.656},{"time":2.6667,"x":0.817,"y":0.972}]},"weapon_line_2":{"translate":[{"x":63.49,"y":106.08},{"time":0.3667,"x":104.94,"y":175.32},{"time":0.4,"x":10.75,"y":17.96},{"time":1.2667,"x":104.94,"y":175.32},{"time":1.3,"x":10.75,"y":17.96},{"time":2.1667,"x":104.94,"y":175.32},{"time":2.2,"x":10.75,"y":17.96},{"time":2.6667,"x":63.49,"y":106.08}],"scale":[{"y":0.81,"curve":0.428,"c2":0.4,"c3":0.814,"c4":0.82},{"time":0.3667,"y":0.583},{"time":0.4,"curve":0.231,"c3":0.656,"c4":0.53},{"time":1.2667,"y":0.583},{"time":1.3,"curve":0.25,"c3":0.832,"c4":0.79},{"time":2.1667,"y":0.583},{"time":2.2,"curve":0.233,"c3":0.639,"c4":0.49},{"time":2.6667,"y":0.81}]},"weapon_line_3":{"translate":[{"x":-7.75,"y":7.37},{"time":0.8667,"x":-112,"y":106.57},{"time":0.9,"x":-7.75,"y":7.37},{"time":1.7667,"x":-112,"y":106.57},{"time":1.8,"x":-7.75,"y":7.37},{"time":2.6333,"x":-112,"y":106.57},{"time":2.6667,"x":-7.75,"y":7.37}],"scale":[{"x":0.86},{"time":0.8667,"x":1.14,"y":0.321},{"time":0.9,"x":0.86},{"time":1.7667,"x":1.14,"y":0.321},{"time":1.8,"x":0.86},{"time":2.6333,"x":1.14,"y":0.321},{"time":2.6667,"x":0.86}]},"weapon_line_4":{"translate":[{"x":117.66,"y":70.14},{"time":0.1,"x":128.96,"y":76.88},{"time":0.1333,"x":31.02,"y":18.49},{"time":0.9667,"x":128.96,"y":76.88},{"time":1,"x":31.02,"y":18.49},{"time":1.8667,"x":128.96,"y":76.88},{"time":1.9,"x":31.02,"y":18.49},{"time":2.6667,"x":117.66,"y":70.14}],"scale":[{"x":1.238,"y":0.227},{"time":0.1,"x":1.28,"y":0.126},{"time":0.1333,"x":0.92},{"time":0.9667,"x":1.28,"y":0.126},{"time":1,"x":0.92},{"time":1.8667,"x":1.28,"y":0.126},{"time":1.9,"x":0.92},{"time":2.6667,"x":1.238,"y":0.227}]},"weapon_line_5":{"translate":[{"x":-63.37,"y":9.87},{"time":0.1,"x":-68.62,"y":10.79,"curve":"stepped"},{"time":0.1333,"x":-24.85,"y":3.1},{"time":1,"x":-68.62,"y":10.79,"curve":"stepped"},{"time":1.0333,"x":-24.85,"y":3.1},{"time":1.9,"x":-68.62,"y":10.79,"curve":"stepped"},{"time":1.9333,"x":-24.85,"y":3.1},{"time":2.6667,"x":-63.37,"y":9.87}],"scale":[{"x":1.265,"y":0.712,"curve":0.396,"c2":0.39,"c3":0.735,"c4":0.73},{"time":0.1,"x":1.32,"y":0.657,"curve":"stepped"},{"time":0.1333,"x":0.98,"curve":0.25,"c3":0.826,"c4":0.76},{"time":1,"x":1.32,"y":0.657,"curve":"stepped"},{"time":1.0333,"x":0.98,"curve":0.25,"c3":0.826,"c4":0.76},{"time":1.9,"x":1.32,"y":0.657,"curve":"stepped"},{"time":1.9333,"x":0.98,"curve":0.239,"c3":0.752,"c4":0.66},{"time":2.6667,"x":1.265,"y":0.712}]},"weapon_line_6":{"rotate":[{"angle":0.93},{"time":0.0333},{"time":0.8667,"angle":0.93},{"time":0.9},{"time":1.7667,"angle":0.93},{"time":1.8},{"time":2.6667,"angle":0.93}],"translate":[{"x":111.54,"y":-55.58},{"time":0.0333,"x":-6.99,"y":3.63},{"time":0.8667,"x":111.54,"y":-55.58},{"time":0.9,"x":-6.99,"y":3.63},{"time":1.7667,"x":111.54,"y":-55.58},{"time":1.8,"x":-6.99,"y":3.63},{"time":2.6667,"x":111.54,"y":-55.58}],"scale":[{"y":0.323},{"time":0.0333},{"time":0.8667,"y":0.323},{"time":0.9},{"time":1.7667,"y":0.323},{"time":1.8},{"time":2.6667,"y":0.323}]},"weapon_line_7":{"translate":[{"x":-13.66,"y":-56.53},{"time":0.6333,"x":-47.03,"y":-194.71},{"time":0.6667,"x":-3.12,"y":-12.9},{"time":1.5333,"x":-47.03,"y":-194.71},{"time":1.5667,"x":-3.12,"y":-12.9},{"time":2.4333,"x":-47.03,"y":-194.71},{"time":2.4667,"x":-3.12,"y":-12.9},{"time":2.6667,"x":-13.66,"y":-56.53}],"scale":[{"x":0.967,"y":0.805},{"time":0.6333,"x":1.18,"y":0.189},{"time":0.6667,"x":0.9},{"time":1.5333,"x":1.18,"y":0.189},{"time":1.5667,"x":0.9},{"time":2.4333,"x":1.18,"y":0.189},{"time":2.4667,"x":0.9},{"time":2.6667,"x":0.967,"y":0.805}]},"front_ef_1_1":{"rotate":[{"angle":-5.1,"curve":"stepped"},{"time":0.5,"angle":-5.1},{"time":1.9667,"curve":"stepped"},{"time":2,"angle":-5.1}],"translate":[{"x":-144.38,"y":-452.67,"curve":"stepped"},{"time":0.5,"x":-144.38,"y":-452.67},{"time":1.9667,"curve":"stepped"},{"time":2,"x":-144.38,"y":-452.67}],"shear":[{"time":0.5},{"time":1.9667,"x":1.94,"curve":"stepped"},{"time":2}]},"front_ef_2_1":{"rotate":[{},{"time":1.4667,"angle":4.8},{"time":1.5}],"translate":[{"x":25.68,"y":-359.52},{"time":1.4667,"x":4.51,"y":60.9},{"time":1.5,"x":25.68,"y":-359.52}],"shear":[{},{"time":1.4667,"x":1.37,"y":-1.95},{"time":1.5}]},"front_ef_3_1":{"rotate":[{"angle":-0.22},{"time":0.1333,"curve":"stepped"},{"time":0.1667,"angle":-2.4,"curve":"stepped"},{"time":1.3333,"angle":-2.4},{"time":2.6667,"angle":-0.22}],"translate":[{"x":-23.32,"y":57.32},{"time":0.1333,"x":-31.44,"y":77.77,"curve":"stepped"},{"time":0.1667,"x":57.9,"y":-147.22,"curve":"stepped"},{"time":1.3333,"x":57.9,"y":-147.22},{"time":2.6667,"x":-23.32,"y":57.32}],"shear":[{"x":-1.49,"y":-8.14},{"time":0.1333,"x":-1.84,"y":-8.95,"curve":"stepped"},{"time":0.1667,"x":2.07,"curve":"stepped"},{"time":1.3333,"x":2.07},{"time":2.6667,"x":-1.49,"y":-8.14}]},"front_ef_4_1":{"rotate":[{"angle":-3.35},{"time":0.6333,"angle":-9.55},{"time":0.6667,"angle":4.8,"curve":"stepped"},{"time":1.8333,"angle":4.8},{"time":2.6667,"angle":-3.35}],"translate":[{"x":15.84,"y":-6.11},{"time":0.6333,"x":-52.57,"y":121.94},{"time":0.6667,"x":105.85,"y":-174.58,"curve":"stepped"},{"time":1.8333,"x":105.85,"y":-174.58},{"time":2.6667,"x":15.84,"y":-6.11}]},"front_ef_5_1":{"rotate":[{},{"time":1.4667,"angle":-10.47,"curve":"stepped"},{"time":1.5}],"translate":[{"x":-17.43,"y":15.36},{"time":1.4667,"x":-188.92,"y":194.2,"curve":"stepped"},{"time":1.5,"x":-17.43,"y":15.36}]},"front_ef_6_1":{"rotate":[{"angle":-7.2},{"time":1.4667,"angle":6.65},{"time":1.5,"angle":-7.2}],"translate":[{"x":-40.98,"y":-71.43},{"time":1.4667,"x":89.36,"y":153.19},{"time":1.5,"x":-40.98,"y":-71.43}]},"front_ef_7_1":{"rotate":[{"time":1.1},{"time":2.5667,"angle":23.94,"curve":"stepped"},{"time":2.6}],"translate":[{"x":-38.05,"y":-48.4,"curve":"stepped"},{"time":1.1,"x":-38.05,"y":-48.4},{"time":2.5667,"x":130.13,"y":56.51,"curve":"stepped"},{"time":2.6,"x":-38.05,"y":-48.4}]},"front_ef_8_1":{"rotate":[{"angle":4.17,"curve":"stepped"},{"time":0.4,"angle":4.17},{"time":1.8667,"angle":-2.89,"curve":"stepped"},{"time":1.9,"angle":4.17}],"translate":[{"x":-19.35,"y":19.84,"curve":"stepped"},{"time":0.4,"x":-19.35,"y":19.84},{"time":1.8667,"x":52.35,"y":-199.15,"curve":"stepped"},{"time":1.9,"x":-19.35,"y":19.84}]},"front_ef_9_1":{"rotate":[{"angle":-5.81},{"time":0.1333,"angle":-6.39,"curve":"stepped"},{"time":0.1667,"curve":"stepped"},{"time":1.3333},{"time":2.6667,"angle":-5.81}],"translate":[{"x":-117.15,"y":-216.44},{"time":0.1333,"x":-128.86,"y":-238.09,"curve":"stepped"},{"time":0.1667,"curve":"stepped"},{"time":1.3333},{"time":2.6667,"x":-117.15,"y":-216.44}],"scale":[{"y":0.956},{"time":0.1333,"y":0.951,"curve":"stepped"},{"time":0.1667,"curve":"stepped"},{"time":1.3333},{"time":2.6667,"y":0.956}],"shear":[{"x":-8.4,"y":-8.83},{"time":0.1333,"x":-9.24,"y":-9.71,"curve":"stepped"},{"time":0.1667,"curve":"stepped"},{"time":1.3333},{"time":2.6667,"x":-8.4,"y":-8.83}]},"front_ef_10_1":{"rotate":[{},{"time":1.4667,"angle":-15.23},{"time":1.5}],"translate":[{},{"time":1.4667,"x":-236.91,"y":-182.67},{"time":1.5}]},"front_ef_11_1":{"rotate":[{"angle":18.75},{"time":1.4667,"angle":8.52,"curve":"stepped"},{"time":1.5,"angle":18.75}],"translate":[{"x":396.64,"y":175.14},{"time":1.4667,"x":170.25,"y":53.99,"curve":"stepped"},{"time":1.5,"x":396.64,"y":175.14}]},"front_ef_13_1":{"rotate":[{"time":0.3667},{"time":1.8333,"angle":-17.45,"curve":"stepped"},{"time":1.8667}],"translate":[{"time":0.3667},{"time":1.8333,"x":-182.37,"y":-18.4,"curve":"stepped"},{"time":1.8667}],"shear":[{"time":0.3667},{"time":1.8333,"x":6.97,"y":13.48,"curve":"stepped"},{"time":1.8667}]},"front_ef_14_1":{"rotate":[{"angle":-6.43},{"time":1.4667,"angle":-25.73,"curve":"stepped"},{"time":1.5,"angle":-6.43}],"translate":[{"x":-61.84,"y":45.92},{"time":1.4667,"x":-247.35,"y":183.68,"curve":"stepped"},{"time":1.5,"x":-61.84,"y":45.92}]},"purple_1":{"translate":[{"x":48.39,"y":-72.06},{"time":2.3333,"x":-30.51,"y":31.03}]},"purple_2":{"translate":[{"x":44.5,"y":-67.72},{"time":0.5667,"curve":"stepped"},{"time":1.7333},{"time":1.7667,"x":115.18,"y":-175.28},{"time":2.6667,"x":44.5,"y":-67.72}]},"purple_3":{"translate":[{"x":-74.78,"y":76.61,"curve":"stepped"},{"time":0.3,"x":-74.78,"y":76.61},{"time":0.3333,"x":56.54,"y":-74.78},{"time":1.8,"x":-74.78,"y":76.61}]},"purple_4":{"translate":[{"x":-81.4,"y":103.47,"curve":0.358,"c2":0.65,"c3":0.693},{"time":0.1333,"x":-84.37,"y":107.25,"curve":0.25,"c3":0.75},{"time":1.3333,"curve":0.245,"c3":0.714,"c4":0.85},{"time":2.6667,"x":-81.4,"y":103.47}]},"purple_5":{"translate":[{"x":-20.65,"y":35.02},{"time":1.3333,"x":-61.94,"y":105.07},{"time":2},{"time":2.6667,"x":-20.65,"y":35.02}]},"purple_6":{"translate":[{},{"time":2.6667,"x":-136.62,"y":171.31}]},"purple_7":{"translate":[{"x":-86.55,"y":159.9},{"time":0.5,"x":-115.4,"y":213.2},{"time":1.1667},{"time":2.6667,"x":-86.55,"y":159.9}]},"purple_8":{"translate":[{"x":-19.53,"y":35.42},{"time":1.3333,"x":-71.59,"y":129.87,"curve":"stepped"},{"time":2.1333,"x":-71.59,"y":129.87},{"time":2.1667},{"time":2.6667,"x":-19.53,"y":35.42}]},"purple_9":{"translate":[{},{"time":2.6667,"x":-69.72,"y":170.92}]},"flower_14":{"rotate":[{"angle":-77.23},{"time":0.4667,"angle":-123.57,"curve":"stepped"},{"time":0.5},{"time":1.3333,"angle":-77.23},{"time":1.8,"angle":-123.57,"curve":"stepped"},{"time":1.8333},{"time":2.6667,"angle":-77.23}],"translate":[{"x":-148.14,"y":349.41},{"time":0.4667,"x":-225.32,"y":514.89,"curve":"stepped"},{"time":0.5,"x":-19.5,"y":73.61},{"time":1.3333,"x":-148.14,"y":349.41},{"time":1.8,"x":-225.32,"y":514.89,"curve":"stepped"},{"time":1.8333,"x":-19.5,"y":73.61},{"time":2.6667,"x":-148.14,"y":349.41}]},"flower_8":{"rotate":[{"angle":-23.71},{"time":0.6333,"angle":-67.84},{"time":0.6667,"angle":21.54},{"time":1.3333,"angle":-23.71},{"time":1.9667,"angle":-67.84},{"time":2,"angle":21.54},{"time":2.6667,"angle":-23.71}],"translate":[{"x":64.12,"y":-99.31},{"time":0.6333,"x":19.06,"y":4.96},{"time":0.6667,"x":110.35,"y":-206.25},{"time":1.3333,"x":64.12,"y":-99.31},{"time":1.9667,"x":19.06,"y":4.96},{"time":2,"x":110.35,"y":-206.25},{"time":2.6667,"x":64.12,"y":-99.31}]},"flower_5":{"rotate":[{"angle":-147.67},{"time":0.4667,"angle":152.19},{"time":0.5,"angle":-47.43},{"time":1.3333,"angle":-147.67},{"time":1.8,"angle":152.19},{"time":1.8333,"angle":-47.43},{"time":2.6667,"angle":-147.67}],"translate":[{"x":-154.5,"y":115.86},{"time":0.4667,"x":-230.58,"y":230.58},{"time":0.5,"x":-27.7,"y":-75.34},{"time":1.3333,"x":-154.5,"y":115.86},{"time":1.8,"x":-230.58,"y":230.58},{"time":1.8333,"x":-27.7,"y":-75.34},{"time":2.6667,"x":-154.5,"y":115.86}]},"flower_4":{"rotate":[{"angle":-178.65},{"time":0.3,"angle":-134.07},{"time":0.3333,"angle":47.59},{"time":1.3333,"angle":-178.65},{"time":1.6333,"angle":-134.07},{"time":1.6667,"angle":47.59},{"time":2.6667,"angle":-178.65}],"translate":[{"x":-556.38,"y":524.67},{"time":0.3,"x":-583.15,"y":582.92},{"time":0.3333,"x":-476.05,"y":349.92},{"time":1.3333,"x":-556.38,"y":524.67},{"time":1.6333,"x":-583.15,"y":582.92},{"time":1.6667,"x":-476.05,"y":349.92},{"time":2.6667,"x":-556.38,"y":524.67}]},"flower_10":{"rotate":[{"angle":42.3},{"time":0.2333,"angle":16.69},{"time":0.2667,"angle":151.57},{"time":1.3333,"angle":42.3},{"time":1.5667,"angle":16.69},{"time":1.6,"angle":151.57},{"time":2.6667,"angle":42.3}],"translate":[{"x":-146.92,"y":739.31},{"time":0.2333,"x":-169.01,"y":789.8},{"time":0.2667,"x":-52.67,"y":523.88},{"time":1.3333,"x":-146.92,"y":739.31},{"time":1.5667,"x":-169.01,"y":789.8},{"time":1.6,"x":-52.67,"y":523.88},{"time":2.6667,"x":-146.92,"y":739.31}]},"flower_15":{"rotate":[{"angle":47},{"time":0.4,"angle":80.61},{"time":0.4333,"angle":-25.6},{"time":1.3333,"angle":47},{"time":1.7333,"angle":80.61},{"time":1.7667,"angle":-25.6},{"time":2.6667,"angle":47}],"translate":[{"x":-28.08,"y":189.34},{"time":0.4,"x":-48.32,"y":256.35},{"time":0.4333,"x":15.62,"y":44.59},{"time":1.3333,"x":-28.08,"y":189.34},{"time":1.7333,"x":-48.32,"y":256.35},{"time":1.7667,"x":15.62,"y":44.59},{"time":2.6667,"x":-28.08,"y":189.34}]},"flower_13":{"rotate":[{"angle":-51.33},{"time":1.1333,"angle":79.38},{"time":1.1667,"angle":-70.27},{"time":1.3333,"angle":-51.33},{"time":2.4667,"angle":79.38},{"time":2.5,"angle":-70.27},{"time":2.6667,"angle":-51.33}],"translate":[{"x":135.08,"y":-14.32},{"time":1.1333,"y":309.31},{"time":1.1667,"x":154.66,"y":-61.22},{"time":1.3333,"x":135.08,"y":-14.32},{"time":2.4667,"y":309.31},{"time":2.5,"x":154.66,"y":-61.22},{"time":2.6667,"x":135.08,"y":-14.32}]},"flower_7":{"rotate":[{"angle":35.79},{"time":0.5667,"angle":114.89},{"time":0.6,"angle":-63.64},{"time":1.3333,"angle":35.79},{"time":1.9,"angle":114.89},{"time":1.9333,"angle":-63.64},{"time":2.6667,"angle":35.79}],"translate":[{"x":-213.42,"y":338.4},{"time":0.5667,"x":-288.89,"y":490.41},{"time":0.6,"x":-118.55,"y":147.31},{"time":1.3333,"x":-213.42,"y":338.4},{"time":1.9,"x":-288.89,"y":490.41},{"time":1.9333,"x":-118.55,"y":147.31},{"time":2.6667,"x":-213.42,"y":338.4}]},"front_ef_12_1":{"rotate":[{"angle":-1.25},{"time":0.5667,"angle":-4.68,"curve":"stepped"},{"time":0.6,"angle":4.2,"curve":"stepped"},{"time":1.7667,"angle":4.2},{"time":2.6667,"angle":-1.25}],"translate":[{"x":-92.51,"y":-37.63},{"time":0.5667,"x":-177.98,"y":-82.28,"curve":"stepped"},{"time":0.6,"x":43.23,"y":33.3,"curve":"stepped"},{"time":1.7667,"x":43.23,"y":33.3},{"time":2.6667,"x":-92.51,"y":-37.63}],"shear":[{"x":0.11,"y":0.78},{"time":0.5667,"x":-0.72,"y":-1.44,"curve":"stepped"},{"time":0.6,"x":1.44,"y":4.29,"curve":"stepped"},{"time":1.7667,"x":1.44,"y":4.29},{"time":2.6667,"x":0.11,"y":0.78}]},"front_ef_15_1":{"rotate":[{"angle":-5.09},{"time":0.9667,"angle":-14.93,"curve":"stepped"},{"time":1,"curve":"stepped"},{"time":2.1667},{"time":2.6667,"angle":-5.09}],"translate":[{"x":-87.15,"y":5.85},{"time":0.9667,"x":-305.86,"y":25.59,"curve":"stepped"},{"time":1,"x":25.98,"y":-4.36,"curve":"stepped"},{"time":2.1667,"x":25.98,"y":-4.36},{"time":2.6667,"x":-87.15,"y":5.85}],"shear":[{"x":-1.23,"y":-1.64},{"time":0.9667,"x":-3.6,"y":-4.8,"curve":"stepped"},{"time":1,"curve":"stepped"},{"time":2.1667},{"time":2.6667,"x":-1.23,"y":-1.64}]},"flare":{"scale":[{"x":0.852,"y":0.852},{"time":1.3,"x":1.316,"y":1.316,"curve":"stepped"},{"time":1.3333,"x":0.852,"y":0.852},{"time":2.6667,"x":1.316,"y":1.316}]},"shadow":{"translate":[{},{"time":2.6333,"x":-74.98},{"time":2.6667}]},"shadow2":{"translate":[{"x":-37.96},{"time":1.3,"x":-74.98},{"time":1.3333},{"time":2.6667,"x":-37.96}]},"shadow3":{"translate":[{},{"time":2.6333,"x":-74.98},{"time":2.6667}]},"shadow4":{"translate":[{"x":-37.96},{"time":1.3,"x":-74.98},{"time":1.3333},{"time":2.6667,"x":-37.96}]},"back_ef_2_2":{"rotate":[{"time":0.8333},{"time":2.3,"angle":50.72,"curve":"stepped"},{"time":2.3333}],"translate":[{"time":0.8333},{"time":2.3,"x":-3.02,"y":159.9,"curve":"stepped"},{"time":2.3333}]},"back_ef_2_3":{"rotate":[{"angle":34.58},{"time":0.4667,"angle":50.72,"curve":"stepped"},{"time":0.5,"curve":"stepped"},{"time":1.6667},{"time":2.6667,"angle":34.58}],"translate":[{"x":-2.06,"y":109.02},{"time":0.4667,"x":-3.02,"y":159.9,"curve":"stepped"},{"time":0.5,"curve":"stepped"},{"time":1.6667},{"time":2.6667,"x":-2.06,"y":109.02}]},"back_ef_1_2":{"rotate":[{"time":0.8333},{"time":2.3,"angle":15.42,"curve":"stepped"},{"time":2.3333}],"translate":[{"time":0.8333},{"time":2.3,"x":-146.7,"y":37.88,"curve":"stepped"},{"time":2.3333}]},"back_ef_1_3":{"rotate":[{"angle":10.51},{"time":0.4667,"angle":15.42,"curve":"stepped"},{"time":0.5,"curve":"stepped"},{"time":1.6667},{"time":2.6667,"angle":10.51}],"translate":[{"x":-100.03,"y":25.82},{"time":0.4667,"x":-146.7,"y":37.88,"curve":"stepped"},{"time":0.5,"curve":"stepped"},{"time":1.6667},{"time":2.6667,"x":-100.03,"y":25.82}]},"back_ef_3_2":{"rotate":[{"time":1.1667},{"time":2.6333,"angle":28.92,"curve":"stepped"},{"time":2.6667}],"translate":[{"time":1.1667},{"time":2.6333,"x":-59.99,"y":133.49,"curve":"stepped"},{"time":2.6667}],"shear":[{"time":1.1667},{"time":2.6333,"x":4.28,"y":15.31,"curve":"stepped"},{"time":2.6667}]},"back_ef_3_3":{"rotate":[{"angle":13.14},{"time":0.8,"angle":28.92,"curve":"stepped"},{"time":0.8333,"curve":"stepped"},{"time":2},{"time":2.6667,"angle":13.14}],"translate":[{"x":-27.27,"y":60.68},{"time":0.8,"x":-59.99,"y":133.49,"curve":"stepped"},{"time":0.8333,"curve":"stepped"},{"time":2},{"time":2.6667,"x":-27.27,"y":60.68}],"shear":[{"x":1.95,"y":6.96},{"time":0.8,"x":4.28,"y":15.31,"curve":"stepped"},{"time":0.8333,"curve":"stepped"},{"time":2},{"time":2.6667,"x":1.95,"y":6.96}]},"front_ef_1_2":{"rotate":[{"angle":-2.2},{"time":0.5,"angle":-0.46},{"time":0.6333,"curve":"stepped"},{"time":0.6667,"angle":-5.1,"curve":"stepped"},{"time":1.8333,"angle":-5.1},{"time":2.6667,"angle":-2.2}],"translate":[{"x":-62.35,"y":-195.47},{"time":0.5,"x":-13.13,"y":-41.15},{"time":0.6333,"curve":"stepped"},{"time":0.6667,"x":-144.38,"y":-452.67,"curve":"stepped"},{"time":1.8333,"x":-144.38,"y":-452.67},{"time":2.6667,"x":-62.35,"y":-195.47}],"shear":[{"x":1.1},{"time":0.5,"x":1.76},{"time":0.6333,"x":1.94,"curve":"stepped"},{"time":0.6667,"curve":"stepped"},{"time":1.8333},{"time":2.6667,"x":1.1}]},"front_ef_2_2":{"rotate":[{"angle":4.36},{"time":0.1333,"angle":4.8},{"time":0.1667,"curve":"stepped"},{"time":1.3333},{"time":2.6667,"angle":4.36}],"translate":[{"x":6.44,"y":22.68},{"time":0.1333,"x":4.51,"y":60.9},{"time":0.1667,"x":25.68,"y":-359.52,"curve":"stepped"},{"time":1.3333,"x":25.68,"y":-359.52},{"time":2.6667,"x":6.44,"y":22.68}],"shear":[{"x":1.25,"y":-1.77},{"time":0.1333,"x":1.37,"y":-1.95},{"time":0.1667,"curve":"stepped"},{"time":1.3333},{"time":2.6667,"x":1.25,"y":-1.77}]},"front_ef_3_2":{"rotate":[{"angle":-2.4},{"time":1.3333,"angle":-0.22},{"time":1.4667,"curve":"stepped"},{"time":1.5,"angle":-2.4}],"translate":[{"x":57.9,"y":-147.22},{"time":1.3333,"x":-23.32,"y":57.32},{"time":1.4667,"x":-31.44,"y":77.77,"curve":"stepped"},{"time":1.5,"x":57.9,"y":-147.22}],"shear":[{"x":2.07},{"time":1.3333,"x":-1.49,"y":-8.14},{"time":1.4667,"x":-1.84,"y":-8.95,"curve":"stepped"},{"time":1.5,"x":2.07}]},"front_ef_4_2":{"rotate":[{"angle":4.8,"curve":"stepped"},{"time":0.5,"angle":4.8},{"time":1.8333,"angle":-8.24},{"time":1.9667,"angle":-9.55},{"time":2,"angle":4.8}],"translate":[{"x":105.85,"y":-174.58,"curve":"stepped"},{"time":0.5,"x":105.85,"y":-174.58},{"time":1.8333,"x":-38.17,"y":94.98},{"time":1.9667,"x":-52.57,"y":121.94},{"time":2,"x":105.85,"y":-174.58}]},"front_ef_5_2":{"rotate":[{"angle":-9.52},{"time":0.1333,"angle":-10.47,"curve":"stepped"},{"time":0.1667,"curve":"stepped"},{"time":1.3333},{"time":2.6667,"angle":-9.52}],"translate":[{"x":-173.33,"y":177.95},{"time":0.1333,"x":-188.92,"y":194.2,"curve":"stepped"},{"time":0.1667,"x":-17.43,"y":15.36,"curve":"stepped"},{"time":1.3333,"x":-17.43,"y":15.36},{"time":2.6667,"x":-173.33,"y":177.95}]},"front_ef_6_2":{"rotate":[{"angle":5.39},{"time":0.1333,"angle":6.65},{"time":0.1667,"angle":-7.2,"curve":"stepped"},{"time":1.3333,"angle":-7.2},{"time":2.6667,"angle":5.39}],"translate":[{"x":77.51,"y":132.77},{"time":0.1333,"x":89.36,"y":153.19},{"time":0.1667,"x":-40.98,"y":-71.43,"curve":"stepped"},{"time":1.3333,"x":-40.98,"y":-71.43},{"time":2.6667,"x":77.51,"y":132.77}]},"front_ef_7_2":{"rotate":[{"angle":3.81},{"time":1.1,"angle":21.76},{"time":1.2333,"angle":23.94,"curve":"stepped"},{"time":1.2667,"curve":"stepped"},{"time":2.4333},{"time":2.6667,"angle":3.81}],"translate":[{"x":-11.29,"y":-31.71},{"time":1.1,"x":114.85,"y":46.98},{"time":1.2333,"x":130.13,"y":56.51,"curve":"stepped"},{"time":1.2667,"x":-38.05,"y":-48.4,"curve":"stepped"},{"time":2.4333,"x":-38.05,"y":-48.4},{"time":2.6667,"x":-11.29,"y":-31.71}]},"front_ef_8_2":{"rotate":[{"angle":-0.32},{"time":0.4,"angle":-2.25},{"time":0.5333,"angle":-2.89,"curve":"stepped"},{"time":0.5667,"angle":4.17,"curve":"stepped"},{"time":1.7333,"angle":4.17},{"time":2.0333,"angle":2.72},{"time":2.6667,"angle":-0.32}],"translate":[{"x":26.27,"y":-119.52},{"time":0.4,"x":45.83,"y":-179.24},{"time":0.5333,"x":52.35,"y":-199.15,"curve":"stepped"},{"time":0.5667,"x":-19.35,"y":19.84,"curve":"stepped"},{"time":1.7333,"x":-19.35,"y":19.84},{"time":2.0333,"x":-4.69,"y":-24.95},{"time":2.6667,"x":26.27,"y":-119.52}]},"front_ef_9_2":{"rotate":[{},{"time":1.3333,"angle":-5.81},{"time":1.4667,"angle":-6.39,"curve":"stepped"},{"time":1.5}],"translate":[{},{"time":1.3333,"x":-117.15,"y":-216.44},{"time":1.4667,"x":-128.86,"y":-238.09,"curve":"stepped"},{"time":1.5}],"scale":[{},{"time":1.3333,"y":0.956},{"time":1.4667,"y":0.951,"curve":"stepped"},{"time":1.5}],"shear":[{},{"time":1.3333,"x":-8.4,"y":-8.83},{"time":1.4667,"x":-9.24,"y":-9.71,"curve":"stepped"},{"time":1.5}]},"front_ef_10_2":{"rotate":[{"angle":-13.84},{"time":0.1333,"angle":-15.23},{"time":0.1667,"curve":"stepped"},{"time":1.3333},{"time":2.6667,"angle":-13.84}],"translate":[{"x":-215.37,"y":-166.07},{"time":0.1333,"x":-236.91,"y":-182.67},{"time":0.1667,"curve":"stepped"},{"time":1.3333},{"time":2.6667,"x":-215.37,"y":-166.07}]},"front_ef_11_2":{"rotate":[{"angle":9.45},{"time":0.1333,"angle":8.52,"curve":"stepped"},{"time":0.1667,"angle":18.75,"curve":"stepped"},{"time":1.3333,"angle":18.75},{"time":2.6667,"angle":9.45}],"translate":[{"x":190.83,"y":65},{"time":0.1333,"x":170.25,"y":53.99,"curve":"stepped"},{"time":0.1667,"x":396.64,"y":175.14,"curve":"stepped"},{"time":1.3333,"x":396.64,"y":175.14},{"time":2.6667,"x":190.83,"y":65}]},"front_ef_12_2":{"rotate":[{"angle":4.2,"curve":"stepped"},{"time":0.4333,"angle":4.2},{"time":1.7667,"angle":-3.87},{"time":1.9,"angle":-4.68,"curve":"stepped"},{"time":1.9333,"angle":4.2}],"translate":[{"x":43.23,"y":33.3,"curve":"stepped"},{"time":0.4333,"x":43.23,"y":33.3},{"time":1.7667,"x":-157.87,"y":-71.78},{"time":1.9,"x":-177.98,"y":-82.28,"curve":"stepped"},{"time":1.9333,"x":43.23,"y":33.3}],"shear":[{"x":1.44,"y":4.29,"curve":"stepped"},{"time":0.4333,"x":1.44,"y":4.29},{"time":1.7667,"x":-0.52,"y":-0.92},{"time":1.9,"x":-0.72,"y":-1.44,"curve":"stepped"},{"time":1.9333,"x":1.44,"y":4.29}]},"front_ef_13_2":{"rotate":[{"angle":-11.5},{"time":0.3667,"angle":-15.86},{"time":0.5,"angle":-17.45,"curve":"stepped"},{"time":0.5333,"curve":"stepped"},{"time":1.7},{"time":2.3667,"angle":-7.93},{"time":2.6667,"angle":-11.5}],"translate":[{"x":-120.2,"y":-12.13},{"time":0.3667,"x":-165.79,"y":-16.73},{"time":0.5,"x":-182.37,"y":-18.4,"curve":"stepped"},{"time":0.5333,"curve":"stepped"},{"time":1.7},{"time":2.3667,"x":-82.9,"y":-8.36},{"time":2.6667,"x":-120.2,"y":-12.13}],"shear":[{"x":4.59,"y":8.88},{"time":0.3667,"x":6.33,"y":12.25},{"time":0.5,"x":6.97,"y":13.48,"curve":"stepped"},{"time":0.5333,"curve":"stepped"},{"time":1.7},{"time":2.3667,"x":3.17,"y":6.13},{"time":2.6667,"x":4.59,"y":8.88}]},"front_ef_14_2":{"rotate":[{"angle":-23.97},{"time":0.1333,"angle":-25.73,"curve":"stepped"},{"time":0.1667,"angle":-6.43,"curve":"stepped"},{"time":1.3333,"angle":-6.43},{"time":2.6667,"angle":-23.97}],"translate":[{"x":-230.48,"y":171.15},{"time":0.1333,"x":-247.35,"y":183.68,"curve":"stepped"},{"time":0.1667,"x":-61.84,"y":45.92,"curve":"stepped"},{"time":1.3333,"x":-61.84,"y":45.92},{"time":2.6667,"x":-230.48,"y":171.15}]},"front_ef_15_2":{"rotate":[{"time":0.8333},{"time":2.1667,"angle":-13.57},{"time":2.3,"angle":-14.93,"curve":"stepped"},{"time":2.3333}],"translate":[{"x":25.98,"y":-4.36,"curve":"stepped"},{"time":0.8333,"x":25.98,"y":-4.36},{"time":2.1667,"x":-275.69,"y":22.87},{"time":2.3,"x":-305.86,"y":25.59,"curve":"stepped"},{"time":2.3333,"x":25.98,"y":-4.36}],"shear":[{"time":0.8333},{"time":2.1667,"x":-3.27,"y":-4.36},{"time":2.3,"x":-3.6,"y":-4.8,"curve":"stepped"},{"time":2.3333}]}}}}}